Workbook

Sheet Trips
A1: Trip_ID | B1: Date | C1: Total_Spent | D1: Time_Spent (min) | E1: Arrival_Time | F1: Busy | G1: Total_Items | H1: Total_Kept | I1: Total_To_Sell | J1: Total_Discarded | K1: Cost_Per_Sellable_Item | L1: Validation
A2: =IF(B2="","",ROW()-1) -> 1 | B2: 45937 | C2: 20.93 | D2: 88 | E2: 0.44930556 | F2: Low | G2: 17 | H2: 2 | I2: 12 | J2: 3 | K2: =IF(I2="","",IF(I2=0,"No sellable items",C2/I2)) -> 1.7441667 | L2: =IF(G2="","",IF(G2=H2+I2+J2,"✓","✗ Mismatch")) -> ✓
A3: =IF(B3="","",ROW()-1) -> 2 | B3: 45953 | C3: 18.28 | D3: 124 | E3: 0.39930556 | F3: Low | G3: 16 | H3: 3 | I3: 10 | J3: 3 | K3: =IF(I3="","",IF(I3=0,"No sellable items",C3/I3)) -> 1.828 | L3: =IF(G3="","",IF(G3=H3+I3+J3,"✓","✗ Mismatch")) -> ✓
A4: =IF(B4="","",ROW()-1) -> 3 | B4: 45965 | C4: 46.04 | D4: 60 | E4: 0.44722222 | F4: Medium | G4: 10 | H4: 3 | I4: 4 | J4: 3 | K4: =IF(I4="","",IF(I4=0,"No sellable items",C4/I4)) -> 11.51 | L4: =IF(G4="","",IF(G4=H4+I4+J4,"✓","✗ Mismatch")) -> ✓
A5: =IF(B5="","",ROW()-1) -> 4 | B5: 45983 | C5: 12.55 | D5: 168 | E5: 0.48472222 | F5: Low | G5: 6 | H5: 1 | I5: 4 | J5: 1 | K5: =IF(I5="","",IF(I5=0,"No sellable items",C5/I5)) -> 3.1375 | L5: =IF(G5="","",IF(G5=H5+I5+J5,"✓","✗ Mismatch")) -> ✓
A6: =IF(B6="","",ROW()-1) -> 5 | B6: 46001 | C6: 46.98 | D6: 139 | E6: 0.48333333 | F6: Low | G6: 7 | H6: 1 | I6: 3 | J6: 3 | K6: =IF(I6="","",IF(I6=0,"No sellable items",C6/I6)) -> 15.66 | L6: =IF(G6="","",IF(G6=H6+I6+J6,"✓","✗ Mismatch")) -> ✓
A7: =IF(B7="","",ROW()-1) -> 6 | B7: 46010 | C7: 48.2 | D7: 170 | E7: 0.43333333 | F7: Low | G7: 16 | H7: 2 | I7: 11 | J7: 3 | K7: =IF(I7="","",IF(I7=0,"No sellable items",C7/I7)) -> 4.3818182 | L7: =IF(G7="","",IF(G7=H7+I7+J7,"✓","✗ Mismatch")) -> ✓
A8: =IF(B8="","",ROW()-1) -> 7 | B8: 46020 | C8: 20.55 | D8: 179 | E8: 0.44305556 | F8: Medium | G8: 14 | H8: 2 | I8: 9 | J8: 3 | K8: =IF(I8="","",IF(I8=0,"No sellable items",C8/I8)) -> 2.2833333 | L8: =IF(G8="","",IF(G8=H8+I8+J8,"✓","✗ Mismatch")) -> ✓
A9: =IF(B9="","",ROW()-1) -> 8 | B9: 46031 | C9: 51.49 | D9: 148 | E9: 0.59305556 | F9: Medium | G9: 6 | H9: 0 | I9: 3 | J9: 3 | K9: =IF(I9="","",IF(I9=0,"No sellable items",C9/I9)) -> 17.163333 | L9: =IF(G9="","",IF(G9=H9+I9+J9,"✓","✗ Mismatch")) -> ✓
A10: =IF(B10="","",ROW()-1) -> 9 | B10: 46041 | C10: 11.11 | D10: 176 | E10: 0.46736111 | F10: Medium | G10: 12 | H10: 3 | I10: 8 | J10: 1 | K10: =IF(I10="","",IF(I10=0,"No sellable items",C10/I10)) -> 1.38875 | L10: =IF(G10="","",IF(G10=H10+I10+J10,"✓","✗ Mismatch")) -> ✓
A11: =IF(B11="","",ROW()-1) -> 10 | B11: 46048 | C11: 19.59 | D11: 131 | E11: 0.59444444 | F11: Medium | G11: 12 | H11: 2 | I11: 8 | J11: 2 | K11: =IF(I11="","",IF(I11=0,"No sellable items",C11/I11)) -> 2.44875 | L11: =IF(G11="","",IF(G11=H11+I11+J11,"✓","✗ Mismatch")) -> ✓
A12: =IF(B12="","",ROW()-1) -> 11 | B12: 46056 | C12: 14.5 | D12: 123 | E12: 0.45 | F12: Low | G12: 7 | H12: 1 | I12: 3 | J12: 3 | K12: =IF(I12="","",IF(I12=0,"No sellable items",C12/I12)) -> 4.8333333 | L12: =IF(G12="","",IF(G12=H12+I12+J12,"✓","✗ Mismatch")) -> ✓
A13: =IF(B13="","",ROW()-1) -> 12 | B13: 46067 | C13: 26.08 | D13: 136 | E13: 0.56458333 | F13: Low | G13: 14 | H13: 2 | I13: 9 | J13: 3 | K13: =IF(I13="","",IF(I13=0,"No sellable items",C13/I13)) -> 2.8977778 | L13: =IF(G13="","",IF(G13=H13+I13+J13,"✓","✗ Mismatch")) -> ✓
... A16: =IF(B16="","",ROW()-1) -> 15 | B16: 46092 | C16: 33.35 | D16: 159 | E16: 0.62361111 | F16: Low | G16: 11 | H16: 1 | I16: 6 | J16: 4 | K16: =IF(I16="","",IF(I16=0,"No sellable items",C16/I16)) -> 5.5583333 | L16: =IF(G16="","",IF(G16=H16+I16+J16,"✓","✗ Mismatch")) -> ✓
A17: =IF(B17="","",ROW()-1) | K17: =IF(I17="","",IF(I17=0,"No sellable items",C17/I17)) | L17: =IF(G17="","",IF(G17=H17+I17+J17,"✓","✗ Mismatch"))
A18: =IF(B18="","",ROW()-1) | K18: =IF(I18="","",IF(I18=0,"No sellable items",C18/I18)) | L18: =IF(G18="","",IF(G18=H18+I18+J18,"✓","✗ Mismatch"))
A19: =IF(B19="","",ROW()-1) | K19: =IF(I19="","",IF(I19=0,"No sellable items",C19/I19)) | L19: =IF(G19="","",IF(G19=H19+I19+J19,"✓","✗ Mismatch"))
A20: =IF(B20="","",ROW()-1) | K20: =IF(I20="","",IF(I20=0,"No sellable items",C20/I20)) | L20: =IF(G20="","",IF(G20=H20+I20+J20,"✓","✗ Mismatch"))
A21: =IF(B21="","",ROW()-1) | K21: =IF(I21="","",IF(I21=0,"No sellable items",C21/I21)) | L21: =IF(G21="","",IF(G21=H21+I21+J21,"✓","✗ Mismatch"))
A22: =IF(B22="","",ROW()-1) | K22: =IF(I22="","",IF(I22=0,"No sellable items",C22/I22)) | L22: =IF(G22="","",IF(G22=H22+I22+J22,"✓","✗ Mismatch"))
A23: =IF(B23="","",ROW()-1) | K23: =IF(I23="","",IF(I23=0,"No sellable items",C23/I23)) | L23: =IF(G23="","",IF(G23=H23+I23+J23,"✓","✗ Mismatch"))
A24: =IF(B24="","",ROW()-1) | K24: =IF(I24="","",IF(I24=0,"No sellable items",C24/I24)) | L24: =IF(G24="","",IF(G24=H24+I24+J24,"✓","✗ Mismatch"))
A25: =IF(B25="","",ROW()-1) | K25: =IF(I25="","",IF(I25=0,"No sellable items",C25/I25)) | L25: =IF(G25="","",IF(G25=H25+I25+J25,"✓","✗ Mismatch"))
A26: =IF(B26="","",ROW()-1) | K26: =IF(I26="","",IF(I26=0,"No sellable items",C26/I26)) | L26: =IF(G26="","",IF(G26=H26+I26+J26,"✓","✗ Mismatch"))
A27: =IF(B27="","",ROW()-1) | K27: =IF(I27="","",IF(I27=0,"No sellable items",C27/I27)) | L27: =IF(G27="","",IF(G27=H27+I27+J27,"✓","✗ Mismatch"))
A28: =IF(B28="","",ROW()-1) | K28: =IF(I28="","",IF(I28=0,"No sellable items",C28/I28)) | L28: =IF(G28="","",IF(G28=H28+I28+J28,"✓","✗ Mismatch"))
... A51: =IF(B51="","",ROW()-1) | K51: =IF(I51="","",IF(I51=0,"No sellable items",C51/I51)) | L51: =IF(G51="","",IF(G51=H51+I51+J51,"✓","✗ Mismatch"))

Sheet Items
A1: SKU | B1: Trip_ID | C1: Brand | D1: Size | E1: Gender | F1: Description | G1: Tags | H1: Condition Notes | I1: Category | J1: Status
A2: =IF(C2="","","T"&TEXT(B2,"000")&"I"&TEXT(COUNTIF(B$2:B2,B2),"000")) -> T001I001 | B2: 1 | C2: J.Crew | D2: S/M | E2: F | F2: navy sunglasses | I2: Accessories | J2: Sell
A3: =IF(C3="","","T"&TEXT(B3,"000")&"I"&TEXT(COUNTIF(B$2:B3,B3),"000")) -> T001I002 | B3: 1 | C3: Levi's | D3: XL | E3: F | F3: pink fitted romper | I3: Jumpsuits/Rompers | J3: Sell
A4: =IF(C4="","","T"&TEXT(B4,"000")&"I"&TEXT(COUNTIF(B$2:B4,B4),"000")) -> T001I003 | B4: 1 | C4: Zara | D4: S | E4: M | F4: green joggers | I4: Bottoms | J4: Sell
A5: =IF(C5="","","T"&TEXT(B5,"000")&"I"&TEXT(COUNTIF(B$2:B5,B5),"000")) -> T001I004 | B5: 1 | C5: Patagonia | D5: L | E5: F | F5: purple wrap dress | I5: Dresses | J5: Sell
A6: =IF(C6="","","T"&TEXT(B6,"000")&"I"&TEXT(COUNTIF(B$2:B6,B6),"000")) -> T001I005 | B6: 1 | C6: Deb | D6: S | E6: F | F6: plaid cotton jeans | I6: Bottoms | J6: Sell
A7: =IF(C7="","","T"&TEXT(B7,"000")&"I"&TEXT(COUNTIF(B$2:B7,B7),"000")) -> T001I006 | B7: 1 | C7: Old Navy | D7: XS | E7: F | F7: navy vintage tank top | I7: Tops | J7: Sell
A8: =IF(C8="","","T"&TEXT(B8,"000")&"I"&TEXT(COUNTIF(B$2:B8,B8),"000")) -> T001I007 | B8: 1 | C8: BKE | D8: S | E8: F | F8: striped boho tank top | I8: Tops | J8: Sell
A9: =IF(C9="","","T"&TEXT(B9,"000")&"I"&TEXT(COUNTIF(B$2:B9,B9),"000")) -> T001I008 | B9: 1 | C9: Levi's | D9: 10 | E9: F | F9: green flats | I9: Footwear | J9: Sell
A10: =IF(C10="","","T"&TEXT(B10,"000")&"I"&TEXT(COUNTIF(B$2:B10,B10),"000")) -> T001I009 | B10: 1 | C10: Express | D10: M | E10: F | F10: red vintage jeans | I10: Bottoms | J10: Sell
A11: =IF(C11="","","T"&TEXT(B11,"000")&"I"&TEXT(COUNTIF(B$2:B11,B11),"000")) -> T001I010 | B11: 1 | C11: H&M | D11: L | E11: F | F11: striped denim tank top | I11: Tops | J11: Sell
A12: =IF(C12="","","T"&TEXT(B12,"000")&"I"&TEXT(COUNTIF(B$2:B12,B12),"000")) -> T001I011 | B12: 1 | C12: LOFT | D12: M | E12: M | F12: olive cotton blouse | I12: Tops | J12: Sell
A13: =IF(C13="","","T"&TEXT(B13,"000")&"I"&TEXT(COUNTIF(B$2:B13,B13),"000")) -> T001I012 | B13: 1 | C13: Express | D13: M | E13: F | F13: gray boho dress | I13: Dresses | J13: Sell
... A15: =IF(C15="","","T"&TEXT(B15,"000")&"I"&TEXT(COUNTIF(B$2:B15,B15),"000")) -> T001I014 | B15: 1 | C15: Urban Outfitters | D15: L | E15: F | F15: striped henley | I15: Tops | J15: Keep
A16: =IF(C16="","","T"&TEXT(B16,"000")&"I"&TEXT(COUNTIF(B$2:B16,B16),"000")) -> T001I015 | B16: 1 | C16: Other | D16: S | E16: M | F16: striped vintage cami | H16: stretched out | I16: Tops | J16: Discard
A17: =IF(C17="","","T"&TEXT(B17,"000")&"I"&TEXT(COUNTIF(B$2:B17,B17),"000")) -> T001I016 | B17: 1 | C17: Nike | D17: M | E17: M | F17: blue button-down shirt | H17: bleach mark | I17: Tops | J17: Discard
A18: =IF(C18="","","T"&TEXT(B18,"000")&"I"&TEXT(COUNTIF(B$2:B18,B18),"000")) -> T001I017 | B18: 1 | C18: Express | D18: M | E18: F | F18: coral y2k tank top | H18: bleach mark | I18: Tops | J18: Discard
A19: =IF(C19="","","T"&TEXT(B19,"000")&"I"&TEXT(COUNTIF(B$2:B19,B19),"000")) -> T002I001 | B19: 2 | C19: Gap | D19: M | E19: F | F19: plaid bodycon dress | I19: Dresses | J19: Sell
A20: =IF(C20="","","T"&TEXT(B20,"000")&"I"&TEXT(COUNTIF(B$2:B20,B20),"000")) -> T002I002 | B20: 2 | C20: Adidas | D20: L | E20: F | F20: coral long sleeve boho shirt | I20: Tops | J20: Sell
A21: =IF(C21="","","T"&TEXT(B21,"000")&"I"&TEXT(COUNTIF(B$2:B21,B21),"000")) -> T002I003 | B21: 2 | C21: Other | D21: S | E21: F | F21: black denim blouse | I21: Tops | J21: Sell
A22: =IF(C22="","","T"&TEXT(B22,"000")&"I"&TEXT(COUNTIF(B$2:B22,B22),"000")) -> T002I004 | B22: 2 | C22: SO Clothing | D22: XS | E22: F | F22: brown bodycon dress | I22: Dresses | J22: Sell
A23: =IF(C23="","","T"&TEXT(B23,"000")&"I"&TEXT(COUNTIF(B$2:B23,B23),"000")) -> T002I005 | B23: 2 | C23: Hollister | D23: 7 | E23: F | F23: striped flats | I23: Footwear | J23: Sell
A24: =IF(C24="","","T"&TEXT(B24,"000")&"I"&TEXT(COUNTIF(B$2:B24,B24),"000")) -> T002I006 | B24: 2 | C24: Nike | D24: M/L | E24: F | F24: pink athletic scarf | I24: Accessories | J24: Sell
A25: =IF(C25="","","T"&TEXT(B25,"000")&"I"&TEXT(COUNTIF(B$2:B25,B25),"000")) -> T002I007 | B25: 2 | C25: Victoria's Secret | D25: M | E25: F | F25: green oversized cami | I25: Tops | J25: Sell
A26: =IF(C26="","","T"&TEXT(B26,"000")&"I"&TEXT(COUNTIF(B$2:B26,B26),"000")) -> T002I008 | B26: 2 | C26: J.Crew | D26: L | E26: F | F26: white mini dress | I26: Dresses | J26: Sell
A27: =IF(C27="","","T"&TEXT(B27,"000")&"I"&TEXT(COUNTIF(B$2:B27,B27),"000")) -> T002I009 | B27: 2 | C27: Apt. 9 | D27: XS | E27: F | F27: brown boho romper | I27: Jumpsuits/Rompers | J27: Sell
A28: =IF(C28="","","T"&TEXT(B28,"000")&"I"&TEXT(COUNTIF(B$2:B28,B28),"000")) -> T002I010 | B28: 2 | C28: Levi's | D28: M | E28: F | F28: pink cotton dress | I28: Dresses | J28: Sell
A29: =IF(C29="","","T"&TEXT(B29,"000")&"I"&TEXT(COUNTIF(B$2:B29,B29),"000")) -> T002I011 | B29: 2 | C29: Free People | D29: M | E29: F | F29: tan lace jeans | I29: Bottoms | J29: Keep
A30: =IF(C30="","","T"&TEXT(B30,"000")&"I"&TEXT(COUNTIF(B$2:B30,B30),"000")) -> T002I012 | B30: 2 | C30: Deb | D30: L | E30: M | F30: gray fitted romper | I30: Jumpsuits/Rompers | J30: Keep
... A33: =IF(C33="","","T"&TEXT(B33,"000")&"I"&TEXT(COUNTIF(B$2:B33,B33),"000")) -> T002I015 | B33: 2 | C33: Other | D33: S | E33: F | F33: red windbreaker | I33: Coats/Jackets | J33: Discard
A34: =IF(C34="","","T"&TEXT(B34,"000")&"I"&TEXT(COUNTIF(B$2:B34,B34),"000")) -> T002I016 | B34: 2 | C34: Free People | D34: S | E34: M | F34: tan cargo pants | H34: hole in seam | I34: Bottoms | J34: Discard
A35: =IF(C35="","","T"&TEXT(B35,"000")&"I"&TEXT(COUNTIF(B$2:B35,B35),"000")) -> T003I001 | B35: 3 | C35: Free People | D35: S | E35: M | F35: purple long sleeve fitted shirt | I35: Tops | J35: Sell
A36: =IF(C36="","","T"&TEXT(B36,"000")&"I"&TEXT(COUNTIF(B$2:B36,B36),"000")) -> T003I002 | B36: 3 | C36: Forever 21 | D36: L | E36: F | F36: red athletic dress | I36: Dresses | J36: Sell
A37: =IF(C37="","","T"&TEXT(B37,"000")&"I"&TEXT(COUNTIF(B$2:B37,B37),"000")) -> T003I003 | B37: 3 | C37: Old Navy | D37: S | E37: F | F37: cream crossbody bag | I37: Accessories | J37: Sell
A38: =IF(C38="","","T"&TEXT(B38,"000")&"I"&TEXT(COUNTIF(B$2:B38,B38),"000")) -> T003I004 | B38: 3 | C38: SO Clothing | D38: M | E38: F | F38: white wide leg pants | I38: Bottoms | J38: Sell
A39: =IF(C39="","","T"&TEXT(B39,"000")&"I"&TEXT(COUNTIF(B$2:B39,B39),"000")) -> T003I005 | B39: 3 | C39: H&M | D39: L | E39: F | F39: purple knit skirt | I39: Bottoms | J39: Keep
A40: =IF(C40="","","T"&TEXT(B40,"000")&"I"&TEXT(COUNTIF(B$2:B40,B40),"000")) -> T003I006 | B40: 3 | C40: Express | D40: S | E40: F | F40: tan cotton dress | I40: Dresses | J40: Keep
A41: =IF(C41="","","T"&TEXT(B41,"000")&"I"&TEXT(COUNTIF(B$2:B41,B41),"000")) -> T003I007 | B41: 3 | C41: Nike | D41: M | E41: F | F41: green leggings | I41: Bottoms | J41: Keep
A42: =IF(C42="","","T"&TEXT(B42,"000")&"I"&TEXT(COUNTIF(B$2:B42,B42),"000")) -> T003I008 | B42: 3 | C42: Other | D42: L | E42: F | F42: coral wide leg pants | I42: Bottoms | J42: Discard
A43: =IF(C43="","","T"&TEXT(B43,"000")&"I"&TEXT(COUNTIF(B$2:B43,B43),"000")) -> T003I009 | B43: 3 | C43: Free People | D43: M | E43: F | F43: olive cropped denim top | H43: heavy pilling | I43: Tops | J43: Discard
A44: =IF(C44="","","T"&TEXT(B44,"000")&"I"&TEXT(COUNTIF(B$2:B44,B44),"000")) -> T003I010 | B44: 3 | C44: Other | D44: L | E44: M | F44: navy leggings | H44: bleach mark | I44: Bottoms | J44: Discard
A45: =IF(C45="","","T"&TEXT(B45,"000")&"I"&TEXT(COUNTIF(B$2:B45,B45),"000")) -> T004I001 | B45: 4 | C45: Other | D45: XS | E45: M | F45: tan maxi dress | I45: Dresses | J45: Sell
A46: =IF(C46="","","T"&TEXT(B46,"000")&"I"&TEXT(COUNTIF(B$2:B46,B46),"000")) -> T004I002 | B46: 4 | C46: Tommy Hilfiger | D46: XS | E46: M | F46: navy denim cami | I46: Tops | J46: Sell
A47: =IF(C47="","","T"&TEXT(B47,"000")&"I"&TEXT(COUNTIF(B$2:B47,B47),"000")) -> T004I003 | B47: 4 | C47: H&M | D47: S | E47: F | F47: coral sundress | I47: Dresses | J47: Sell
A48: =IF(C48="","","T"&TEXT(B48,"000")&"I"&TEXT(COUNTIF(B$2:B48,B48),"000")) -> T004I004 | B48: 4 | C48: LOFT | D48: L | E48: M | F48: teal casual dress | I48: Dresses | J48: Sell
A49: =IF(C49="","","T"&TEXT(B49,"000")&"I"&TEXT(COUNTIF(B$2:B49,B49),"000")) -> T004I005 | B49: 4 | C49: LOFT | D49: S/M | E49: F | F49: olive boho scarf | I49: Accessories | J49: Keep
A50: =IF(C50="","","T"&TEXT(B50,"000")&"I"&TEXT(COUNTIF(B$2:B50,B50),"000")) -> T004I006 | B50: 4 | C50: Tommy Hilfiger | D50: XL | E50: F | F50: tie-dye sundress | H50: bleach mark | I50: Dresses | J50: Discard
A51: =IF(C51="","","T"&TEXT(B51,"000")&"I"&TEXT(COUNTIF(B$2:B51,B51),"000")) -> T005I001 | B51: 5 | C51: H&M | D51: M | E51: F | F51: olive swim cover-up | I51: Swimwear | J51: Sell
A52: =IF(C52="","","T"&TEXT(B52,"000")&"I"&TEXT(COUNTIF(B$2:B52,B52),"000")) -> T005I002 | B52: 5 | C52: Patagonia | D52: 10 | E52: F | F52: brown sandals | I52: Footwear | J52: Sell
A53: =IF(C53="","","T"&TEXT(B53,"000")&"I"&TEXT(COUNTIF(B$2:B53,B53),"000")) -> T005I003 | B53: 5 | C53: Express | D53: S | E53: F | F53: navy button-down shirt | I53: Tops | J53: Sell
A54: =IF(C54="","","T"&TEXT(B54,"000")&"I"&TEXT(COUNTIF(B$2:B54,B54),"000")) -> T005I004 | B54: 5 | C54: LOFT | D54: S | E54: F | F54: teal joggers | I54: Bottoms | J54: Keep
A55: =IF(C55="","","T"&TEXT(B55,"000")&"I"&TEXT(COUNTIF(B$2:B55,B55),"000")) -> T005I005 | B55: 5 | C55: American Eagle | D55: S | E55: F | F55: plaid knit jeans | H55: heavy pilling | I55: Bottoms | J55: Discard
A56: =IF(C56="","","T"&TEXT(B56,"000")&"I"&TEXT(COUNTIF(B$2:B56,B56),"000")) -> T005I006 | B56: 5 | C56: Free People | D56: L | E56: M | F56: striped joggers | H56: stretched out | I56: Bottoms | J56: Discard
A57: =IF(C57="","","T"&TEXT(B57,"000")&"I"&TEXT(COUNTIF(B$2:B57,B57),"000")) -> T005I007 | B57: 5 | C57: American Eagle | D57: S | E57: F | F57: burgundy sundress | H57: heavy pilling | I57: Dresses | J57: Discard
A58: =IF(C58="","","T"&TEXT(B58,"000")&"I"&TEXT(COUNTIF(B$2:B58,B58),"000")) -> T006I001 | B58: 6 | C58: Adidas | D58: M | E58: F | F58: pink sundress | I58: Dresses | J58: Sell
A59: =IF(C59="","","T"&TEXT(B59,"000")&"I"&TEXT(COUNTIF(B$2:B59,B59),"000")) -> T006I002 | B59: 6 | C59: American Eagle | D59: M | E59: F | F59: teal boho bikini top | I59: Swimwear | J59: Sell
A60: =IF(C60="","","T"&TEXT(B60,"000")&"I"&TEXT(COUNTIF(B$2:B60,B60),"000")) -> T006I003 | B60: 6 | C60: BKE | D60: S | E60: F | F60: cream lace sweater | I60: Tops | J60: Sell
A61: =IF(C61="","","T"&TEXT(B61,"000")&"I"&TEXT(COUNTIF(B$2:B61,B61),"000")) -> T006I004 | B61: 6 | C61: The North Face | D61: L | E61: F | F61: navy wide leg pants | I61: Bottoms | J61: Sell
A62: =IF(C62="","","T"&TEXT(B62,"000")&"I"&TEXT(COUNTIF(B$2:B62,B62),"000")) -> T006I005 | B62: 6 | C62: Free People | D62: XL | E62: F | F62: white vintage shorts | I62: Bottoms | J62: Sell
A63: =IF(C63="","","T"&TEXT(B63,"000")&"I"&TEXT(COUNTIF(B$2:B63,B63),"000")) -> T006I006 | B63: 6 | C63: Hollister | D63: XS | E63: F | F63: burgundy graphic tee | I63: Tops | J63: Sell
A64: =IF(C64="","","T"&TEXT(B64,"000")&"I"&TEXT(COUNTIF(B$2:B64,B64),"000")) -> T006I007 | B64: 6 | C64: Victoria's Secret | D64: M | E64: F | F64: blue one-piece swimsuit | I64: Swimwear | J64: Sell
A65: =IF(C65="","","T"&TEXT(B65,"000")&"I"&TEXT(COUNTIF(B$2:B65,B65),"000")) -> T006I008 | B65: 6 | C65: SO Clothing | D65: S | E65: F | F65: red puffer vest | I65: Coats/Jackets | J65: Sell
A66: =IF(C66="","","T"&TEXT(B66,"000")&"I"&TEXT(COUNTIF(B$2:B66,B66),"000")) -> T006I009 | B66: 6 | C66: Free People | D66: L | E66: M | F66: green henley | I66: Tops | J66: Sell
A67: =IF(C67="","","T"&TEXT(B67,"000")&"I"&TEXT(COUNTIF(B$2:B67,B67),"000")) -> T006I010 | B67: 6 | C67: Aerie | D67: 8 | E67: F | F67: red heels | I67: Footwear | J67: Sell
A68: =IF(C68="","","T"&TEXT(B68,"000")&"I"&TEXT(COUNTIF(B$2:B68,B68),"000")) -> T006I011 | B68: 6 | C68: Calvin Klein | D68: M | E68: F | F68: cream button-down shirt | I68: Tops | J68: Sell
A69: =IF(C69="","","T"&TEXT(B69,"000")&"I"&TEXT(COUNTIF(B$2:B69,B69),"000")) -> T006I012 | B69: 6 | C69: Guess | D69: S | E69: M | F69: olive overall shorts | I69: Jumpsuits/Rompers | J69: Keep
A70: =IF(C70="","","T"&TEXT(B70,"000")&"I"&TEXT(COUNTIF(B$2:B70,B70),"000")) -> T006I013 | B70: 6 | C70: LOFT | D70: M | E70: F | F70: striped denim cami | I70: Tops | J70: Keep
A71: =IF(C71="","","T"&TEXT(B71,"000")&"I"&TEXT(COUNTIF(B$2:B71,B71),"000")) -> T006I014 | B71: 6 | C71: Zara | D71: M | E71: F | F71: navy athletic romper | H71: heavy pilling | I71: Jumpsuits/Rompers | J71: Discard
A72: =IF(C72="","","T"&TEXT(B72,"000")&"I"&TEXT(COUNTIF(B$2:B72,B72),"000")) -> T006I015 | B72: 6 | C72: Gap | D72: M | E72: F | F72: burgundy lace jeans | H72: hole in seam | I72: Bottoms | J72: Discard
A73: =IF(C73="","","T"&TEXT(B73,"000")&"I"&TEXT(COUNTIF(B$2:B73,B73),"000")) -> T006I016 | B73: 6 | C73: Forever 21 | D73: S | E73: F | F73: striped wide leg pants | H73: bleach mark | I73: Bottoms | J73: Discard
A74: =IF(C74="","","T"&TEXT(B74,"000")&"I"&TEXT(COUNTIF(B$2:B74,B74),"000")) -> T007I001 | B74: 7 | C74: Hollister | D74: L | E74: F | F74: burgundy fitted tank top | I74: Tops | J74: Sell
A75: =IF(C75="","","T"&TEXT(B75,"000")&"I"&TEXT(COUNTIF(B$2:B75,B75),"000")) -> T007I002 | B75: 7 | C75: Other | D75: XS | E75: F | F75: gray joggers | I75: Bottoms | J75: Sell
A76: =IF(C76="","","T"&TEXT(B76,"000")&"I"&TEXT(COUNTIF(B$2:B76,B76),"000")) -> T007I003 | B76: 7 | C76: Other | D76: M | E76: F | F76: purple cargo pants | I76: Bottoms | J76: Sell
A77: =IF(C77="","","T"&TEXT(B77,"000")&"I"&TEXT(COUNTIF(B$2:B77,B77),"000")) -> T007I004 | B77: 7 | C77: Zara | D77: S | E77: F | F77: red cropped oversized top | I77: Tops | J77: Sell
A78: =IF(C78="","","T"&TEXT(B78,"000")&"I"&TEXT(COUNTIF(B$2:B78,B78),"000")) -> T007I005 | B78: 7 | C78: American Eagle | D78: S | E78: F | F78: brown cardigan | I78: Coats/Jackets | J78: Sell
A79: =IF(C79="","","T"&TEXT(B79,"000")&"I"&TEXT(COUNTIF(B$2:B79,B79),"000")) -> T007I006 | B79: 7 | C79: Aerie | D79: M | E79: M | F79: tan denim jacket | I79: Coats/Jackets | J79: Sell
A80: =IF(C80="","","T"&TEXT(B80,"000")&"I"&TEXT(COUNTIF(B$2:B80,B80),"000")) -> T007I007 | B80: 7 | C80: J.Crew | D80: L | E80: F | F80: white cotton top | I80: Tops | J80: Sell
A81: =IF(C81="","","T"&TEXT(B81,"000")&"I"&TEXT(COUNTIF(B$2:B81,B81),"000")) -> T007I008 | B81: 7 | C81: Nike | D81: M | E81: F | F81: black ribbed bikini top | I81: Swimwear | J81: Sell
A82: =IF(C82="","","T"&TEXT(B82,"000")&"I"&TEXT(COUNTIF(B$2:B82,B82),"000")) -> T007I009 | B82: 7 | C82: Gap | D82: S | E82: M | F82: burgundy wide leg pants | I82: Bottoms | J82: Sell
A83: =IF(C83="","","T"&TEXT(B83,"000")&"I"&TEXT(COUNTIF(B$2:B83,B83),"000")) -> T007I010 | B83: 7 | C83: Ralph Lauren | D83: XS | E83: F | F83: pink boho jeans | I83: Bottoms | J83: Keep
A84: =IF(C84="","","T"&TEXT(B84,"000")&"I"&TEXT(COUNTIF(B$2:B84,B84),"000")) -> T007I011 | B84: 7 | C84: Tommy Hilfiger | D84: XS | E84: F | F84: tie-dye swim cover-up | I84: Swimwear | J84: Keep
A85: =IF(C85="","","T"&TEXT(B85,"000")&"I"&TEXT(COUNTIF(B$2:B85,B85),"000")) -> T007I012 | B85: 7 | C85: Calvin Klein | D85: M | E85: F | F85: tan ribbed sweater | H85: heavy pilling | I85: Tops | J85: Discard
A86: =IF(C86="","","T"&TEXT(B86,"000")&"I"&TEXT(COUNTIF(B$2:B86,B86),"000")) -> T007I013 | B86: 7 | C86: Nike | D86: M | E86: F | F86: green maxi dress | H86: stretched out | I86: Dresses | J86: Discard
A87: =IF(C87="","","T"&TEXT(B87,"000")&"I"&TEXT(COUNTIF(B$2:B87,B87),"000")) -> T007I014 | B87: 7 | C87: Express | D87: M | E87: F | F87: olive henley | H87: bleach mark | I87: Tops | J87: Discard
A88: =IF(C88="","","T"&TEXT(B88,"000")&"I"&TEXT(COUNTIF(B$2:B88,B88),"000")) -> T008I001 | B88: 8 | C88: Zara | D88: S | E88: F | F88: navy fitted sweater | I88: Tops | J88: Sell
A89: =IF(C89="","","T"&TEXT(B89,"000")&"I"&TEXT(COUNTIF(B$2:B89,B89),"000")) -> T008I002 | B89: 8 | C89: Old Navy | D89: L | E89: F | F89: teal y2k tank top | I89: Tops | J89: Sell
A90: =IF(C90="","","T"&TEXT(B90,"000")&"I"&TEXT(COUNTIF(B$2:B90,B90),"000")) -> T008I003 | B90: 8 | C90: American Eagle | D90: XL | E90: F | F90: white boho dress | I90: Dresses | J90: Sell
A91: =IF(C91="","","T"&TEXT(B91,"000")&"I"&TEXT(COUNTIF(B$2:B91,B91),"000")) -> T008I004 | B91: 8 | C91: Calvin Klein | D91: L | E91: M | F91: red sundress | H91: stretched out | I91: Dresses | J91: Discard
A92: =IF(C92="","","T"&TEXT(B92,"000")&"I"&TEXT(COUNTIF(B$2:B92,B92),"000")) -> T008I005 | B92: 8 | C92: Nike | D92: S | E92: F | F92: navy corduroy pants | H92: stain on front | I92: Bottoms | J92: Discard
A93: =IF(C93="","","T"&TEXT(B93,"000")&"I"&TEXT(COUNTIF(B$2:B93,B93),"000")) -> T008I006 | B93: 8 | C93: Self Esteem | D93: M | E93: F | F93: plaid denim jacket | H93: stain on front | I93: Coats/Jackets | J93: Discard
A94: =IF(C94="","","T"&TEXT(B94,"000")&"I"&TEXT(COUNTIF(B$2:B94,B94),"000")) -> T009I001 | B94: 9 | C94: Urban Outfitters | D94: S | E94: F | F94: burgundy maxi dress | I94: Dresses | J94: Sell
A95: =IF(C95="","","T"&TEXT(B95,"000")&"I"&TEXT(COUNTIF(B$2:B95,B95),"000")) -> T009I002 | B95: 9 | C95: Other | D95: S | E95: F | F95: navy swim cover-up | I95: Swimwear | J95: Sell
A96: =IF(C96="","","T"&TEXT(B96,"000")&"I"&TEXT(COUNTIF(B$2:B96,B96),"000")) -> T009I003 | B96: 9 | C96: J.Crew | D96: L | E96: M | F96: teal cropped oversized top | I96: Tops | J96: Sell
A97: =IF(C97="","","T"&TEXT(B97,"000")&"I"&TEXT(COUNTIF(B$2:B97,B97),"000")) -> T009I004 | B97: 9 | C97: Forever 21 | D97: M | E97: F | F97: olive y2k dress | I97: Dresses | J97: Sell
A98: =IF(C98="","","T"&TEXT(B98,"000")&"I"&TEXT(COUNTIF(B$2:B98,B98),"000")) -> T009I005 | B98: 9 | C98: Nike | D98: XL | E98: F | F98: black button-down shirt | I98: Tops | J98: Sell
A99: =IF(C99="","","T"&TEXT(B99,"000")&"I"&TEXT(COUNTIF(B$2:B99,B99),"000")) -> T009I006 | B99: 9 | C99: Candie's | D99: XS | E99: F | F99: olive corduroy pants | I99: Bottoms | J99: Sell
A100: =IF(C100="","","T"&TEXT(B100,"000")&"I"&TEXT(COUNTIF(B$2:B100,B100),"000")) -> T009I007 | B100: 9 | C100: Old Navy | D100: XL | E100: F | F100: red corduroy pants | I100: Bottoms | J100: Sell
A101: =IF(C101="","","T"&TEXT(B101,"000")&"I"&TEXT(COUNTIF(B$2:B101,B101),"000")) -> T009I008 | B101: 9 | C101: Abercrombie & Fitch | D101: S | E101: F | F101: black bodycon dress | I101: Dresses | J101: Sell
A102: =IF(C102="","","T"&TEXT(B102,"000")&"I"&TEXT(COUNTIF(B$2:B102,B102),"000")) -> T009I009 | B102: 9 | C102: H&M | D102: L | E102: F | F102: pink denim blouse | I102: Tops | J102: Keep
A103: =IF(C103="","","T"&TEXT(B103,"000")&"I"&TEXT(COUNTIF(B$2:B103,B103),"000")) -> T009I010 | B103: 9 | C103: Hollister | D103: L | E103: F | F103: burgundy casual sweater | I103: Tops | J103: Keep
...

Sheet Listings
A1: Listing_ID | B1: SKU | C1: Listing_Date | D1: Original_Price | E1: Condition | F1: Condition Notes | G1: Package_Size | H1: Brand_Lookup | I1: Category_Lookup | J1: Match_Key
A2: =IF(B2="","",ROW()-1) -> 1 | B2: T001I002 | C2: 45939 | D2: 17 | E2: Used - Good | F2: minor fading | G2: M | H2: =IF(B2="","",VLOOKUP(B2,Items!A:I,3,FALSE)) -> Levi's | I2: =IF(B2="","",VLOOKUP(B2,Items!A:I,9,FALSE)) -> Jumpsuits/Rompers | J2: =IF(B2="","",TEXT(C2,"MM/DD/YYYY")&H2&I2) -> 10/09/2025Levi'sJumpsuits/Rompers
A3: =IF(B3="","",ROW()-1) -> 2 | B3: T001I008 | C3: 45939 | D3: 30 | E3: Like New | G3: S | H3: =IF(B3="","",VLOOKUP(B3,Items!A:I,3,FALSE)) -> Levi's | I3: =IF(B3="","",VLOOKUP(B3,Items!A:I,9,FALSE)) -> Footwear | J3: =IF(B3="","",TEXT(C3,"MM/DD/YYYY")&H3&I3) -> 10/09/2025Levi'sFootwear
A4: =IF(B4="","",ROW()-1) -> 3 | B4: T001I005 | C4: 45941 | D4: 29 | E4: Used - Good | G4: M | H4: =IF(B4="","",VLOOKUP(B4,Items!A:I,3,FALSE)) -> Deb | I4: =IF(B4="","",VLOOKUP(B4,Items!A:I,9,FALSE)) -> Bottoms | J4: =IF(B4="","",TEXT(C4,"MM/DD/YYYY")&H4&I4) -> 10/11/2025DebBottoms
A5: =IF(B5="","",ROW()-1) -> 4 | B5: T001I001 | C5: 45942 | D5: 20 | E5: Used - Good | G5: XS | H5: =IF(B5="","",VLOOKUP(B5,Items!A:I,3,FALSE)) -> J.Crew | I5: =IF(B5="","",VLOOKUP(B5,Items!A:I,9,FALSE)) -> Accessories | J5: =IF(B5="","",TEXT(C5,"MM/DD/YYYY")&H5&I5) -> 10/12/2025J.CrewAccessories
A6: =IF(B6="","",ROW()-1) -> 5 | B6: T001I010 | C6: 45943 | D6: 20 | E6: Used - Good | F6: minor fading | G6: S | H6: =IF(B6="","",VLOOKUP(B6,Items!A:I,3,FALSE)) -> H&M | I6: =IF(B6="","",VLOOKUP(B6,Items!A:I,9,FALSE)) -> Tops | J6: =IF(B6="","",TEXT(C6,"MM/DD/YYYY")&H6&I6) -> 10/13/2025H&MTops
A7: =IF(B7="","",ROW()-1) -> 6 | B7: T001I009 | C7: 45944 | D7: 18 | E7: Used - Good | F7: small mark on back | G7: M | H7: =IF(B7="","",VLOOKUP(B7,Items!A:I,3,FALSE)) -> Express | I7: =IF(B7="","",VLOOKUP(B7,Items!A:I,9,FALSE)) -> Bottoms | J7: =IF(B7="","",TEXT(C7,"MM/DD/YYYY")&H7&I7) -> 10/14/2025ExpressBottoms
A8: =IF(B8="","",ROW()-1) -> 7 | B8: T001I011 | C8: 45947 | D8: 14 | E8: Used - Excellent | F8: like new condition | G8: S | H8: =IF(B8="","",VLOOKUP(B8,Items!A:I,3,FALSE)) -> LOFT | I8: =IF(B8="","",VLOOKUP(B8,Items!A:I,9,FALSE)) -> Tops | J8: =IF(B8="","",TEXT(C8,"MM/DD/YYYY")&H8&I8) -> 10/17/2025LOFTTops
A9: =IF(B9="","",ROW()-1) -> 8 | B9: T001I007 | C9: 45949 | D9: 24 | E9: Used - Excellent | G9: XS | H9: =IF(B9="","",VLOOKUP(B9,Items!A:I,3,FALSE)) -> BKE | I9: =IF(B9="","",VLOOKUP(B9,Items!A:I,9,FALSE)) -> Tops | J9: =IF(B9="","",TEXT(C9,"MM/DD/YYYY")&H9&I9) -> 10/19/2025BKETops
A10: =IF(B10="","",ROW()-1) -> 9 | B10: T001I004 | C10: 45950 | D10: 23 | E10: Used - Excellent | G10: L | H10: =IF(B10="","",VLOOKUP(B10,Items!A:I,3,FALSE)) -> Patagonia | I10: =IF(B10="","",VLOOKUP(B10,Items!A:I,9,FALSE)) -> Dresses | J10: =IF(B10="","",TEXT(C10,"MM/DD/YYYY")&H10&I10) -> 10/20/2025PatagoniaDresses
A11: =IF(B11="","",ROW()-1) -> 10 | B11: T001I003 | C11: 45951 | D11: 14 | E11: Used - Excellent | F11: like new condition | G11: M | H11: =IF(B11="","",VLOOKUP(B11,Items!A:I,3,FALSE)) -> Zara | I11: =IF(B11="","",VLOOKUP(B11,Items!A:I,9,FALSE)) -> Bottoms | J11: =IF(B11="","",TEXT(C11,"MM/DD/YYYY")&H11&I11) -> 10/21/2025ZaraBottoms
A12: =IF(B12="","",ROW()-1) -> 11 | B12: T002I003 | C12: 45955 | D12: 13 | E12: Used - Excellent | G12: S | H12: =IF(B12="","",VLOOKUP(B12,Items!A:I,3,FALSE)) -> Other | I12: =IF(B12="","",VLOOKUP(B12,Items!A:I,9,FALSE)) -> Tops | J12: =IF(B12="","",TEXT(C12,"MM/DD/YYYY")&H12&I12) -> 10/25/2025OtherTops
A13: =IF(B13="","",ROW()-1) -> 12 | B13: T002I006 | C13: 45957 | D13: 8 | E13: Used - Good | G13: XXS | H13: =IF(B13="","",VLOOKUP(B13,Items!A:I,3,FALSE)) -> Nike | I13: =IF(B13="","",VLOOKUP(B13,Items!A:I,9,FALSE)) -> Accessories | J13: =IF(B13="","",TEXT(C13,"MM/DD/YYYY")&H13&I13) -> 10/27/2025NikeAccessories
A14: =IF(B14="","",ROW()-1) -> 13 | B14: T002I001 | C14: 45961 | D14: 40 | E14: Used - Excellent | G14: M | H14: =IF(B14="","",VLOOKUP(B14,Items!A:I,3,FALSE)) -> Gap | I14: =IF(B14="","",VLOOKUP(B14,Items!A:I,9,FALSE)) -> Dresses | J14: =IF(B14="","",TEXT(C14,"MM/DD/YYYY")&H14&I14) -> 10/31/2025GapDresses
A15: =IF(B15="","",ROW()-1) -> 14 | B15: T002I008 | C15: 45961 | D15: 25 | E15: Used - Good | F15: small mark on back | G15: S | H15: =IF(B15="","",VLOOKUP(B15,Items!A:I,3,FALSE)) -> J.Crew | I15: =IF(B15="","",VLOOKUP(B15,Items!A:I,9,FALSE)) -> Dresses | J15: =IF(B15="","",TEXT(C15,"MM/DD/YYYY")&H15&I15) -> 10/31/2025J.CrewDresses
A16: =IF(B16="","",ROW()-1) -> 15 | B16: T002I004 | C16: 45962 | D16: 28 | E16: Brand New | F16: tags still attached | G16: M | H16: =IF(B16="","",VLOOKUP(B16,Items!A:I,3,FALSE)) -> SO Clothing | I16: =IF(B16="","",VLOOKUP(B16,Items!A:I,9,FALSE)) -> Dresses | J16: =IF(B16="","",TEXT(C16,"MM/DD/YYYY")&H16&I16) -> 11/01/2025SO ClothingDresses
A17: =IF(B17="","",ROW()-1) -> 16 | B17: T002I009 | C17: 45962 | D17: 12 | E17: Like New | G17: M | H17: =IF(B17="","",VLOOKUP(B17,Items!A:I,3,FALSE)) -> Apt. 9 | I17: =IF(B17="","",VLOOKUP(B17,Items!A:I,9,FALSE)) -> Jumpsuits/Rompers | J17: =IF(B17="","",TEXT(C17,"MM/DD/YYYY")&H17&I17) -> 11/01/2025Apt. 9Jumpsuits/Rompers
A18: =IF(B18="","",ROW()-1) -> 17 | B18: T002I002 | C18: 45963 | D18: 5 | E18: Like New | G18: S | H18: =IF(B18="","",VLOOKUP(B18,Items!A:I,3,FALSE)) -> Adidas | I18: =IF(B18="","",VLOOKUP(B18,Items!A:I,9,FALSE)) -> Tops | J18: =IF(B18="","",TEXT(C18,"MM/DD/YYYY")&H18&I18) -> 11/02/2025AdidasTops
A19: =IF(B19="","",ROW()-1) -> 18 | B19: T002I010 | C19: 45965 | D19: 26 | E19: Like New | G19: M | H19: =IF(B19="","",VLOOKUP(B19,Items!A:I,3,FALSE)) -> Levi's | I19: =IF(B19="","",VLOOKUP(B19,Items!A:I,9,FALSE)) -> Dresses | J19: =IF(B19="","",TEXT(C19,"MM/DD/YYYY")&H19&I19) -> 11/04/2025Levi'sDresses
A20: =IF(B20="","",ROW()-1) -> 19 | B20: T002I005 | C20: 45966 | D20: 12 | E20: Used - Excellent | G20: M | H20: =IF(B20="","",VLOOKUP(B20,Items!A:I,3,FALSE)) -> Hollister | I20: =IF(B20="","",VLOOKUP(B20,Items!A:I,9,FALSE)) -> Footwear | J20: =IF(B20="","",TEXT(C20,"MM/DD/YYYY")&H20&I20) -> 11/05/2025HollisterFootwear
A21: =IF(B21="","",ROW()-1) -> 20 | B21: T002I007 | C21: 45966 | D21: 19 | E21: Used - Good | F21: minor fading | G21: S | H21: =IF(B21="","",VLOOKUP(B21,Items!A:I,3,FALSE)) -> Victoria's Secret | I21: =IF(B21="","",VLOOKUP(B21,Items!A:I,9,FALSE)) -> Tops | J21: =IF(B21="","",TEXT(C21,"MM/DD/YYYY")&H21&I21) -> 11/05/2025Victoria's SecretTops
A22: =IF(B22="","",ROW()-1) -> 21 | B22: T003I001 | C22: 45970 | D22: 20 | E22: Used - Excellent | F22: like new condition | G22: M | H22: =IF(B22="","",VLOOKUP(B22,Items!A:I,3,FALSE)) -> Free People | I22: =IF(B22="","",VLOOKUP(B22,Items!A:I,9,FALSE)) -> Tops | J22: =IF(B22="","",TEXT(C22,"MM/DD/YYYY")&H22&I22) -> 11/09/2025Free PeopleTops
A23: =IF(B23="","",ROW()-1) -> 22 | B23: T003I004 | C23: 45971 | D23: 22 | E23: Used - Good | F23: light wear | G23: S | H23: =IF(B23="","",VLOOKUP(B23,Items!A:I,3,FALSE)) -> SO Clothing | I23: =IF(B23="","",VLOOKUP(B23,Items!A:I,9,FALSE)) -> Bottoms | J23: =IF(B23="","",TEXT(C23,"MM/DD/YYYY")&H23&I23) -> 11/10/2025SO ClothingBottoms
A24: =IF(B24="","",ROW()-1) -> 23 | B24: T003I002 | C24: 45978 | D24: 35 | E24: Used - Good | F24: small mark on back | G24: S | H24: =IF(B24="","",VLOOKUP(B24,Items!A:I,3,FALSE)) -> Forever 21 | I24: =IF(B24="","",VLOOKUP(B24,Items!A:I,9,FALSE)) -> Dresses | J24: =IF(B24="","",TEXT(C24,"MM/DD/YYYY")&H24&I24) -> 11/17/2025Forever 21Dresses
A25: =IF(B25="","",ROW()-1) -> 24 | B25: T004I001 | C25: 45989 | D25: 32 | E25: Used - Excellent | G25: M | H25: =IF(B25="","",VLOOKUP(B25,Items!A:I,3,FALSE)) -> Other | I25: =IF(B25="","",VLOOKUP(B25,Items!A:I,9,FALSE)) -> Dresses | J25: =IF(B25="","",TEXT(C25,"MM/DD/YYYY")&H25&I25) -> 11/28/2025OtherDresses
A26: =IF(B26="","",ROW()-1) -> 25 | B26: T004I003 | C26: 45990 | D26: 30 | E26: Used - Excellent | F26: barely worn | G26: L | H26: =IF(B26="","",VLOOKUP(B26,Items!A:I,3,FALSE)) -> H&M | I26: =IF(B26="","",VLOOKUP(B26,Items!A:I,9,FALSE)) -> Dresses | J26: =IF(B26="","",TEXT(C26,"MM/DD/YYYY")&H26&I26) -> 11/29/2025H&MDresses
A27: =IF(B27="","",ROW()-1) -> 26 | B27: T004I004 | C27: 45991 | D27: 29 | E27: Used - Good | F27: light wear | G27: S | H27: =IF(B27="","",VLOOKUP(B27,Items!A:I,3,FALSE)) -> LOFT | I27: =IF(B27="","",VLOOKUP(B27,Items!A:I,9,FALSE)) -> Dresses | J27: =IF(B27="","",TEXT(C27,"MM/DD/YYYY")&H27&I27) -> 11/30/2025LOFTDresses
A28: =IF(B28="","",ROW()-1) -> 27 | B28: T004I002 | C28: 45992 | D28: 14 | E28: Brand New | G28: XS | H28: =IF(B28="","",VLOOKUP(B28,Items!A:I,3,FALSE)) -> Tommy Hilfiger | I28: =IF(B28="","",VLOOKUP(B28,Items!A:I,9,FALSE)) -> Tops | J28: =IF(B28="","",TEXT(C28,"MM/DD/YYYY")&H28&I28) -> 12/01/2025Tommy HilfigerTops
A29: =IF(B29="","",ROW()-1) -> 28 | B29: T005I002 | C29: 46004 | D29: 12 | E29: Used - Fair | F29: small snag near hem | G29: L | H29: =IF(B29="","",VLOOKUP(B29,Items!A:I,3,FALSE)) -> Patagonia | I29: =IF(B29="","",VLOOKUP(B29,Items!A:I,9,FALSE)) -> Footwear | J29: =IF(B29="","",TEXT(C29,"MM/DD/YYYY")&H29&I29) -> 12/13/2025PatagoniaFootwear
A30: =IF(B30="","",ROW()-1) -> 29 | B30: T005I003 | C30: 46009 | D30: 7 | E30: Used - Fair | F30: slight fading | G30: S | H30: =IF(B30="","",VLOOKUP(B30,Items!A:I,3,FALSE)) -> Express | I30: =IF(B30="","",VLOOKUP(B30,Items!A:I,9,FALSE)) -> Tops | J30: =IF(B30="","",TEXT(C30,"MM/DD/YYYY")&H30&I30) -> 12/18/2025ExpressTops
A31: =IF(B31="","",ROW()-1) -> 30 | B31: T006I007 | C31: 46012 | D31: 15 | E31: Used - Good | G31: XXS | H31: =IF(B31="","",VLOOKUP(B31,Items!A:I,3,FALSE)) -> Victoria's Secret | I31: =IF(B31="","",VLOOKUP(B31,Items!A:I,9,FALSE)) -> Swimwear | J31: =IF(B31="","",TEXT(C31,"MM/DD/YYYY")&H31&I31) -> 12/21/2025Victoria's SecretSwimwear
A32: =IF(B32="","",ROW()-1) -> 31 | B32: T006I001 | C32: 46012 | D32: 34 | E32: Used - Good | F32: small mark on back | G32: M | H32: =IF(B32="","",VLOOKUP(B32,Items!A:I,3,FALSE)) -> Adidas | I32: =IF(B32="","",VLOOKUP(B32,Items!A:I,9,FALSE)) -> Dresses | J32: =IF(B32="","",TEXT(C32,"MM/DD/YYYY")&H32&I32) -> 12/21/2025AdidasDresses
A33: =IF(B33="","",ROW()-1) -> 32 | B33: T006I011 | C33: 46012 | D33: 6 | E33: Used - Excellent | F33: barely worn | G33: S | H33: =IF(B33="","",VLOOKUP(B33,Items!A:I,3,FALSE)) -> Calvin Klein | I33: =IF(B33="","",VLOOKUP(B33,Items!A:I,9,FALSE)) -> Tops | J33: =IF(B33="","",TEXT(C33,"MM/DD/YYYY")&H33&I33) -> 12/21/2025Calvin KleinTops
A34: =IF(B34="","",ROW()-1) -> 33 | B34: T006I010 | C34: 46013 | D34: 26 | E34: Used - Good | G34: S | H34: =IF(B34="","",VLOOKUP(B34,Items!A:I,3,FALSE)) -> Aerie | I34: =IF(B34="","",VLOOKUP(B34,Items!A:I,9,FALSE)) -> Footwear | J34: =IF(B34="","",TEXT(C34,"MM/DD/YYYY")&H34&I34) -> 12/22/2025AerieFootwear
A35: =IF(B35="","",ROW()-1) -> 34 | B35: T005I001 | C35: 46015 | D35: 8 | E35: Used - Excellent | F35: like new condition | G35: XS | H35: =IF(B35="","",VLOOKUP(B35,Items!A:I,3,FALSE)) -> H&M | I35: =IF(B35="","",VLOOKUP(B35,Items!A:I,9,FALSE)) -> Swimwear | J35: =IF(B35="","",TEXT(C35,"MM/DD/YYYY")&H35&I35) -> 12/24/2025H&MSwimwear
A36: =IF(B36="","",ROW()-1) -> 35 | B36: T006I008 | C36: 46016 | D36: 18 | E36: Used - Excellent | G36: L | H36: =IF(B36="","",VLOOKUP(B36,Items!A:I,3,FALSE)) -> SO Clothing | I36: =IF(B36="","",VLOOKUP(B36,Items!A:I,9,FALSE)) -> Coats/Jackets | J36: =IF(B36="","",TEXT(C36,"MM/DD/YYYY")&H36&I36) -> 12/25/2025SO ClothingCoats/Jackets
A37: =IF(B37="","",ROW()-1) -> 36 | B37: T006I005 | C37: 46017 | D37: 16 | E37: Used - Good | G37: S | H37: =IF(B37="","",VLOOKUP(B37,Items!A:I,3,FALSE)) -> Free People | I37: =IF(B37="","",VLOOKUP(B37,Items!A:I,9,FALSE)) -> Bottoms | J37: =IF(B37="","",TEXT(C37,"MM/DD/YYYY")&H37&I37) -> 12/26/2025Free PeopleBottoms
A38: =IF(B38="","",ROW()-1) -> 37 | B38: T006I003 | C38: 46019 | D38: 21 | E38: Used - Excellent | F38: like new condition | G38: XS | H38: =IF(B38="","",VLOOKUP(B38,Items!A:I,3,FALSE)) -> BKE | I38: =IF(B38="","",VLOOKUP(B38,Items!A:I,9,FALSE)) -> Tops | J38: =IF(B38="","",TEXT(C38,"MM/DD/YYYY")&H38&I38) -> 12/28/2025BKETops
A39: =IF(B39="","",ROW()-1) -> 38 | B39: T006I002 | C39: 46020 | D39: 9 | E39: Used - Fair | F39: slight fading | G39: XS | H39: =IF(B39="","",VLOOKUP(B39,Items!A:I,3,FALSE)) -> American Eagle | I39: =IF(B39="","",VLOOKUP(B39,Items!A:I,9,FALSE)) -> Swimwear | J39: =IF(B39="","",TEXT(C39,"MM/DD/YYYY")&H39&I39) -> 12/29/2025American EagleSwimwear
A40: =IF(B40="","",ROW()-1) -> 39 | B40: T007I001 | C40: 46022 | D40: 20 | E40: Like New | G40: XS | H40: =IF(B40="","",VLOOKUP(B40,Items!A:I,3,FALSE)) -> Hollister | I40: =IF(B40="","",VLOOKUP(B40,Items!A:I,9,FALSE)) -> Tops | J40: =IF(B40="","",TEXT(C40,"MM/DD/YYYY")&H40&I40) -> 12/31/2025HollisterTops
A41: =IF(B41="","",ROW()-1) -> 40 | B41: T006I004 | C41: 46022 | D41: 25 | E41: Used - Excellent | G41: M | H41: =IF(B41="","",VLOOKUP(B41,Items!A:I,3,FALSE)) -> The North Face | I41: =IF(B41="","",VLOOKUP(B41,Items!A:I,9,FALSE)) -> Bottoms | J41: =IF(B41="","",TEXT(C41,"MM/DD/YYYY")&H41&I41) -> 12/31/2025The North FaceBottoms
A42: =IF(B42="","",ROW()-1) -> 41 | B42: T006I006 | C42: 46023 | D42: 23 | E42: Used - Excellent | G42: S | H42: =IF(B42="","",VLOOKUP(B42,Items!A:I,3,FALSE)) -> Hollister | I42: =IF(B42="","",VLOOKUP(B42,Items!A:I,9,FALSE)) -> Tops | J42: =IF(B42="","",TEXT(C42,"MM/DD/YYYY")&H42&I42) -> 01/01/2026HollisterTops
A43: =IF(B43="","",ROW()-1) -> 42 | B43: T007I009 | C43: 46024 | D43: 22 | E43: Used - Good | G43: M | H43: =IF(B43="","",VLOOKUP(B43,Items!A:I,3,FALSE)) -> Gap | I43: =IF(B43="","",VLOOKUP(B43,Items!A:I,9,FALSE)) -> Bottoms | J43: =IF(B43="","",TEXT(C43,"MM/DD/YYYY")&H43&I43) -> 01/02/2026GapBottoms
A44: =IF(B44="","",ROW()-1) -> 43 | B44: T007I002 | C44: 46026 | D44: 18 | E44: Used - Good | F44: minor fading | G44: M | H44: =IF(B44="","",VLOOKUP(B44,Items!A:I,3,FALSE)) -> Other | I44: =IF(B44="","",VLOOKUP(B44,Items!A:I,9,FALSE)) -> Bottoms | J44: =IF(B44="","",TEXT(C44,"MM/DD/YYYY")&H44&I44) -> 01/04/2026OtherBottoms
A45: =IF(B45="","",ROW()-1) -> 44 | B45: T007I007 | C45: 46030 | D45: 23 | E45: Used - Good | F45: small mark on back | G45: S | H45: =IF(B45="","",VLOOKUP(B45,Items!A:I,3,FALSE)) -> J.Crew | I45: =IF(B45="","",VLOOKUP(B45,Items!A:I,9,FALSE)) -> Tops | J45: =IF(B45="","",TEXT(C45,"MM/DD/YYYY")&H45&I45) -> 01/08/2026J.CrewTops
A46: =IF(B46="","",ROW()-1) -> 45 | B46: T007I004 | C46: 46031 | D46: 18 | E46: Used - Excellent | F46: like new condition | G46: S | H46: =IF(B46="","",VLOOKUP(B46,Items!A:I,3,FALSE)) -> Zara | I46: =IF(B46="","",VLOOKUP(B46,Items!A:I,9,FALSE)) -> Tops | J46: =IF(B46="","",TEXT(C46,"MM/DD/YYYY")&H46&I46) -> 01/09/2026ZaraTops
A47: =IF(B47="","",ROW()-1) -> 46 | B47: T007I005 | C47: 46032 | D47: 25 | E47: Like New | G47: XL | H47: =IF(B47="","",VLOOKUP(B47,Items!A:I,3,FALSE)) -> American Eagle | I47: =IF(B47="","",VLOOKUP(B47,Items!A:I,9,FALSE)) -> Coats/Jackets | J47: =IF(B47="","",TEXT(C47,"MM/DD/YYYY")&H47&I47) -> 01/10/2026American EagleCoats/Jackets
A48: =IF(B48="","",ROW()-1) -> 47 | B48: T007I003 | C48: 46032 | D48: 29 | E48: Used - Excellent | F48: barely worn | G48: M | H48: =IF(B48="","",VLOOKUP(B48,Items!A:I,3,FALSE)) -> Other | I48: =IF(B48="","",VLOOKUP(B48,Items!A:I,9,FALSE)) -> Bottoms | J48: =IF(B48="","",TEXT(C48,"MM/DD/YYYY")&H48&I48) -> 01/10/2026OtherBottoms
A49: =IF(B49="","",ROW()-1) -> 48 | B49: T007I008 | C49: 46033 | D49: 13 | E49: Like New | G49: XXS | H49: =IF(B49="","",VLOOKUP(B49,Items!A:I,3,FALSE)) -> Nike | I49: =IF(B49="","",VLOOKUP(B49,Items!A:I,9,FALSE)) -> Swimwear | J49: =IF(B49="","",TEXT(C49,"MM/DD/YYYY")&H49&I49) -> 01/11/2026NikeSwimwear
A50: =IF(B50="","",ROW()-1) -> 49 | B50: T008I001 | C50: 46035 | D50: 15 | E50: Used - Excellent | F50: like new condition | G50: S | H50: =IF(B50="","",VLOOKUP(B50,Items!A:I,3,FALSE)) -> Zara | I50: =IF(B50="","",VLOOKUP(B50,Items!A:I,9,FALSE)) -> Tops | J50: =IF(B50="","",TEXT(C50,"MM/DD/YYYY")&H50&I50) -> 01/13/2026ZaraTops
A51: =IF(B51="","",ROW()-1) -> 50 | B51: T008I002 | C51: 46039 | D51: 22 | E51: Brand New | G51: S | H51: =IF(B51="","",VLOOKUP(B51,Items!A:I,3,FALSE)) -> Old Navy | I51: =IF(B51="","",VLOOKUP(B51,Items!A:I,9,FALSE)) -> Tops | J51: =IF(B51="","",TEXT(C51,"MM/DD/YYYY")&H51&I51) -> 01/17/2026Old NavyTops
A52: =IF(B52="","",ROW()-1) -> 51 | B52: T009I008 | C52: 46044 | D52: 19 | E52: Used - Fair | F52: tag is worn | G52: L | H52: =IF(B52="","",VLOOKUP(B52,Items!A:I,3,FALSE)) -> Abercrombie & Fitch | I52: =IF(B52="","",VLOOKUP(B52,Items!A:I,9,FALSE)) -> Dresses | J52: =IF(B52="","",TEXT(C52,"MM/DD/YYYY")&H52&I52) -> 01/22/2026Abercrombie & FitchDresses
A53: =IF(B53="","",ROW()-1) -> 52 | B53: T008I003 | C53: 46045 | D53: 12 | E53: Used - Excellent | F53: barely worn | G53: M | H53: =IF(B53="","",VLOOKUP(B53,Items!A:I,3,FALSE)) -> American Eagle | I53: =IF(B53="","",VLOOKUP(B53,Items!A:I,9,FALSE)) -> Dresses | J53: =IF(B53="","",TEXT(C53,"MM/DD/YYYY")&H53&I53) -> 01/23/2026American EagleDresses
A54: =IF(B54="","",ROW()-1) -> 53 | B54: T009I001 | C54: 46046 | D54: 24 | E54: Used - Excellent | G54: M | H54: =IF(B54="","",VLOOKUP(B54,Items!A:I,3,FALSE)) -> Urban Outfitters | I54: =IF(B54="","",VLOOKUP(B54,Items!A:I,9,FALSE)) -> Dresses | J54: =IF(B54="","",TEXT(C54,"MM/DD/YYYY")&H54&I54) -> 01/24/2026Urban OutfittersDresses
A55: =IF(B55="","",ROW()-1) -> 54 | B55: T009I003 | C55: 46047 | D55: 9 | E55: Like New | G55: XS | H55: =IF(B55="","",VLOOKUP(B55,Items!A:I,3,FALSE)) -> J.Crew | I55: =IF(B55="","",VLOOKUP(B55,Items!A:I,9,FALSE)) -> Tops | J55: =IF(B55="","",TEXT(C55,"MM/DD/YYYY")&H55&I55) -> 01/25/2026J.CrewTops
A56: =IF(B56="","",ROW()-1) -> 55 | B56: T009I007 | C56: 46049 | D56: 24 | E56: Used - Good | G56: M | H56: =IF(B56="","",VLOOKUP(B56,Items!A:I,3,FALSE)) -> Old Navy | I56: =IF(B56="","",VLOOKUP(B56,Items!A:I,9,FALSE)) -> Bottoms | J56: =IF(B56="","",TEXT(C56,"MM/DD/YYYY")&H56&I56) -> 01/27/2026Old NavyBottoms
A57: =IF(B57="","",ROW()-1) -> 56 | B57: T009I006 | C57: 46051 | D57: 14 | E57: Like New | G57: M | H57: =IF(B57="","",VLOOKUP(B57,Items!A:I,3,FALSE)) -> Candie's | I57: =IF(B57="","",VLOOKUP(B57,Items!A:I,9,FALSE)) -> Bottoms | J57: =IF(B57="","",TEXT(C57,"MM/DD/YYYY")&H57&I57) -> 01/29/2026Candie'sBottoms
A58: =IF(B58="","",ROW()-1) -> 57 | B58: T010I005 | C58: 46052 | D58: 6 | E58: Used - Good | F58: small mark on back | G58: XS | H58: =IF(B58="","",VLOOKUP(B58,Items!A:I,3,FALSE)) -> Victoria's Secret | I58: =IF(B58="","",VLOOKUP(B58,Items!A:I,9,FALSE)) -> Accessories | J58: =IF(B58="","",TEXT(C58,"MM/DD/YYYY")&H58&I58) -> 01/30/2026Victoria's SecretAccessories
A59: =IF(B59="","",ROW()-1) -> 58 | B59: T009I005 | C59: 46055 | D59: 8 | E59: Used - Good | G59: XS | H59: =IF(B59="","",VLOOKUP(B59,Items!A:I,3,FALSE)) -> Nike | I59: =IF(B59="","",VLOOKUP(B59,Items!A:I,9,FALSE)) -> Tops | J59: =IF(B59="","",TEXT(C59,"MM/DD/YYYY")&H59&I59) -> 02/02/2026NikeTops
A60: =IF(B60="","",ROW()-1) -> 59 | B60: T010I008 | C60: 46056 | D60: 38 | E60: Brand New | G60: L | H60: =IF(B60="","",VLOOKUP(B60,Items!A:I,3,FALSE)) -> Hollister | I60: =IF(B60="","",VLOOKUP(B60,Items!A:I,9,FALSE)) -> Dresses | J60: =IF(B60="","",TEXT(C60,"MM/DD/YYYY")&H60&I60) -> 02/03/2026HollisterDresses
A61: =IF(B61="","",ROW()-1) -> 60 | B61: T010I003 | C61: 46057 | D61: 18 | E61: Used - Excellent | G61: M | H61: =IF(B61="","",VLOOKUP(B61,Items!A:I,3,FALSE)) -> Gap | I61: =IF(B61="","",VLOOKUP(B61,Items!A:I,9,FALSE)) -> Bottoms | J61: =IF(B61="","",TEXT(C61,"MM/DD/YYYY")&H61&I61) -> 02/04/2026GapBottoms
A62: =IF(B62="","",ROW()-1) -> 61 | B62: T010I002 | C62: 46059 | D62: 19 | E62: Used - Good | G62: M | H62: =IF(B62="","",VLOOKUP(B62,Items!A:I,3,FALSE)) -> J.Crew | I62: =IF(B62="","",VLOOKUP(B62,Items!A:I,9,FALSE)) -> Dresses | J62: =IF(B62="","",TEXT(C62,"MM/DD/YYYY")&H62&I62) -> 02/06/2026J.CrewDresses
A63: =IF(B63="","",ROW()-1) -> 62 | B63: T011I001 | C63: 46059 | D63: 35 | E63: Used - Good | F63: minor fading | G63: M | H63: =IF(B63="","",VLOOKUP(B63,Items!A:I,3,FALSE)) -> Forever 21 | I63: =IF(B63="","",VLOOKUP(B63,Items!A:I,9,FALSE)) -> Dresses | J63: =IF(B63="","",TEXT(C63,"MM/DD/YYYY")&H63&I63) -> 02/06/2026Forever 21Dresses
A64: =IF(B64="","",ROW()-1) -> 63 | B64: T010I004 | C64: 46061 | D64: 15 | E64: Used - Fair | F64: light stain on front | G64: M | H64: =IF(B64="","",VLOOKUP(B64,Items!A:I,3,FALSE)) -> Cotton Natural | I64: =IF(B64="","",VLOOKUP(B64,Items!A:I,9,FALSE)) -> Bottoms | J64: =IF(B64="","",TEXT(C64,"MM/DD/YYYY")&H64&I64) -> 02/08/2026Cotton NaturalBottoms
A65: =IF(B65="","",ROW()-1) -> 64 | B65: T010I006 | C65: 46062 | D65: 19 | E65: Used - Good | F65: small mark on back | G65: S | H65: =IF(B65="","",VLOOKUP(B65,Items!A:I,3,FALSE)) -> Free People | I65: =IF(B65="","",VLOOKUP(B65,Items!A:I,9,FALSE)) -> Tops | J65: =IF(B65="","",TEXT(C65,"MM/DD/YYYY")&H65&I65) -> 02/09/2026Free PeopleTops
A66: =IF(B66="","",ROW()-1) -> 65 | B66: T012I001 | C66: 46070 | D66: 39 | E66: Used - Excellent | F66: like new condition | G66: S | H66: =IF(B66="","",VLOOKUP(B66,Items!A:I,3,FALSE)) -> H&M | I66: =IF(B66="","",VLOOKUP(B66,Items!A:I,9,FALSE)) -> Dresses | J66: =IF(B66="","",TEXT(C66,"MM/DD/YYYY")&H66&I66) -> 02/17/2026H&MDresses
A67: =IF(B67="","",ROW()-1) -> 66 | B67: T012I008 | C67: 46070 | D67: 9 | E67: Like New | G67: S | H67: =IF(B67="","",VLOOKUP(B67,Items!A:I,3,FALSE)) -> Nike | I67: =IF(B67="","",VLOOKUP(B67,Items!A:I,9,FALSE)) -> Bottoms | J67: =IF(B67="","",TEXT(C67,"MM/DD/YYYY")&H67&I67) -> 02/17/2026NikeBottoms
A68: =IF(B68="","",ROW()-1) -> 67 | B68: T013I003 | C68: 46077 | D68: 21 | E68: Used - Good | F68: minor fading | G68: S | H68: =IF(B68="","",VLOOKUP(B68,Items!A:I,3,FALSE)) -> Adidas | I68: =IF(B68="","",VLOOKUP(B68,Items!A:I,9,FALSE)) -> Tops | J68: =IF(B68="","",TEXT(C68,"MM/DD/YYYY")&H68&I68) -> 02/24/2026AdidasTops
A69: =IF(B69="","",ROW()-1) -> 68 | B69: T013I004 | C69: 46077 | D69: 27 | E69: Used - Good | G69: S | H69: =IF(B69="","",VLOOKUP(B69,Items!A:I,3,FALSE)) -> Express | I69: =IF(B69="","",VLOOKUP(B69,Items!A:I,9,FALSE)) -> Bottoms | J69: =IF(B69="","",TEXT(C69,"MM/DD/YYYY")&H69&I69) -> 02/24/2026ExpressBottoms
A70: =IF(B70="","",ROW()-1) -> 69 | B70: T012I006 | C70: 46077 | D70: 29 | E70: Used - Excellent | F70: like new condition | G70: M | H70: =IF(B70="","",VLOOKUP(B70,Items!A:I,3,FALSE)) -> Banana Republic | I70: =IF(B70="","",VLOOKUP(B70,Items!A:I,9,FALSE)) -> Dresses | J70: =IF(B70="","",TEXT(C70,"MM/DD/YYYY")&H70&I70) -> 02/24/2026Banana RepublicDresses
A71: =IF(B71="","",ROW()-1) -> 70 | B71: T012I005 | C71: 46080 | D71: 11 | E71: Used - Excellent | F71: like new condition | G71: M | H71: =IF(B71="","",VLOOKUP(B71,Items!A:I,3,FALSE)) -> Express | I71: =IF(B71="","",VLOOKUP(B71,Items!A:I,9,FALSE)) -> Bottoms | J71: =IF(B71="","",TEXT(C71,"MM/DD/YYYY")&H71&I71) -> 02/27/2026ExpressBottoms
A72: =IF(B72="","",ROW()-1) -> 71 | B72: T012I007 | C72: 46080 | D72: 33 | E72: Used - Excellent | G72: M | H72: =IF(B72="","",VLOOKUP(B72,Items!A:I,3,FALSE)) -> Self Esteem | I72: =IF(B72="","",VLOOKUP(B72,Items!A:I,9,FALSE)) -> Dresses | J72: =IF(B72="","",TEXT(C72,"MM/DD/YYYY")&H72&I72) -> 02/27/2026Self EsteemDresses
A73: =IF(B73="","",ROW()-1) -> 72 | B73: T013I002 | C73: 46082 | D73: 23 | E73: Used - Excellent | G73: M | H73: =IF(B73="","",VLOOKUP(B73,Items!A:I,3,FALSE)) -> Tommy Hilfiger | I73: =IF(B73="","",VLOOKUP(B73,Items!A:I,9,FALSE)) -> Tops | J73: =IF(B73="","",TEXT(C73,"MM/DD/YYYY")&H73&I73) -> 03/01/2026Tommy HilfigerTops
A74: =IF(B74="","",ROW()-1) -> 73 | B74: T013I001 | C74: 46085 | D74: 18 | E74: Used - Excellent | G74: XS | H74: =IF(B74="","",VLOOKUP(B74,Items!A:I,3,FALSE)) -> Deb | I74: =IF(B74="","",VLOOKUP(B74,Items!A:I,9,FALSE)) -> Tops | J74: =IF(B74="","",TEXT(C74,"MM/DD/YYYY")&H74&I74) -> 03/04/2026DebTops
A75: =IF(B75="","",ROW()-1) -> 74 | B75: T014I009 | C75: 46086 | D75: 20 | E75: Used - Excellent | G75: S | H75: =IF(B75="","",VLOOKUP(B75,Items!A:I,3,FALSE)) -> Apt. 9 | I75: =IF(B75="","",VLOOKUP(B75,Items!A:I,9,FALSE)) -> Tops | J75: =IF(B75="","",TEXT(C75,"MM/DD/YYYY")&H75&I75) -> 03/05/2026Apt. 9Tops
A76: =IF(B76="","",ROW()-1) -> 75 | B76: T014I004 | C76: 46087 | D76: 16 | E76: Like New | G76: S | H76: =IF(B76="","",VLOOKUP(B76,Items!A:I,3,FALSE)) -> Ralph Lauren | I76: =IF(B76="","",VLOOKUP(B76,Items!A:I,9,FALSE)) -> Tops | J76: =IF(B76="","",TEXT(C76,"MM/DD/YYYY")&H76&I76) -> 03/06/2026Ralph LaurenTops
A77: =IF(B77="","",ROW()-1) -> 76 | B77: T014I006 | C77: 46087 | D77: 24 | E77: Used - Fair | F77: light stain on front | G77: S | H77: =IF(B77="","",VLOOKUP(B77,Items!A:I,3,FALSE)) -> Free People | I77: =IF(B77="","",VLOOKUP(B77,Items!A:I,9,FALSE)) -> Tops | J77: =IF(B77="","",TEXT(C77,"MM/DD/YYYY")&H77&I77) -> 03/06/2026Free PeopleTops
A78: =IF(B78="","",ROW()-1) -> 77 | B78: T014I001 | C78: 46090 | D78: 19 | E78: Used - Good | F78: light wear | G78: S | H78: =IF(B78="","",VLOOKUP(B78,Items!A:I,3,FALSE)) -> Forever 21 | I78: =IF(B78="","",VLOOKUP(B78,Items!A:I,9,FALSE)) -> Bottoms | J78: =IF(B78="","",TEXT(C78,"MM/DD/YYYY")&H78&I78) -> 03/09/2026Forever 21Bottoms
A79: =IF(B79="","",ROW()-1) -> 78 | B79: T014I008 | C79: 46092 | D79: 20 | E79: Used - Good | G79: M | H79: =IF(B79="","",VLOOKUP(B79,Items!A:I,3,FALSE)) -> Aerie | I79: =IF(B79="","",VLOOKUP(B79,Items!A:I,9,FALSE)) -> Jumpsuits/Rompers | J79: =IF(B79="","",TEXT(C79,"MM/DD/YYYY")&H79&I79) -> 03/11/2026AerieJumpsuits/Rompers
A80: =IF(B80="","",ROW()-1) -> 79 | B80: T014I002 | C80: 46092 | D80: 13 | E80: Used - Fair | F80: minor pilling | G80: S | H80: =IF(B80="","",VLOOKUP(B80,Items!A:I,3,FALSE)) -> Self Esteem | I80: =IF(B80="","",VLOOKUP(B80,Items!A:I,9,FALSE)) -> Bottoms | J80: =IF(B80="","",TEXT(C80,"MM/DD/YYYY")&H80&I80) -> 03/11/2026Self EsteemBottoms
A81: =IF(B81="","",ROW()-1) -> 80 | B81: T014I005 | C81: 46095 | D81: 21 | E81: Used - Excellent | G81: L | H81: =IF(B81="","",VLOOKUP(B81,Items!A:I,3,FALSE)) -> Aerie | I81: =IF(B81="","",VLOOKUP(B81,Items!A:I,9,FALSE)) -> Dresses | J81: =IF(B81="","",TEXT(C81,"MM/DD/YYYY")&H81&I81) -> 03/14/2026AerieDresses
A82: =IF(B82="","",ROW()-1) -> 81 | B82: T014I003 | C82: 46096 | D82: 11 | E82: Used - Excellent | G82: S | H82: =IF(B82="","",VLOOKUP(B82,Items!A:I,3,FALSE)) -> Nike | I82: =IF(B82="","",VLOOKUP(B82,Items!A:I,9,FALSE)) -> Tops | J82: =IF(B82="","",TEXT(C82,"MM/DD/YYYY")&H82&I82) -> 03/15/2026NikeTops
A83: =IF(B83="","",ROW()-1) -> 82 | B83: T015I006 | C83: 46096 | D83: 12 | E83: Used - Excellent | G83: L | H83: =IF(B83="","",VLOOKUP(B83,Items!A:I,3,FALSE)) -> Express | I83: =IF(B83="","",VLOOKUP(B83,Items!A:I,9,FALSE)) -> Footwear | J83: =IF(B83="","",TEXT(C83,"MM/DD/YYYY")&H83&I83) -> 03/15/2026ExpressFootwear
A84: =IF(B84="","",ROW()-1) -> 83 | B84: T015I003 | C84: 46096 | D84: 25 | E84: Used - Excellent | G84: S | H84: =IF(B84="","",VLOOKUP(B84,Items!A:I,3,FALSE)) -> Zara | I84: =IF(B84="","",VLOOKUP(B84,Items!A:I,9,FALSE)) -> Tops | J84: =IF(B84="","",TEXT(C84,"MM/DD/YYYY")&H84&I84) -> 03/15/2026ZaraTops
A85: =IF(B85="","",ROW()-1) -> 84 | B85: T015I004 | C85: 46102 | D85: 12 | E85: Used - Excellent | G85: S | H85: =IF(B85="","",VLOOKUP(B85,Items!A:I,3,FALSE)) -> Victoria's Secret | I85: =IF(B85="","",VLOOKUP(B85,Items!A:I,9,FALSE)) -> Tops | J85: =IF(B85="","",TEXT(C85,"MM/DD/YYYY")&H85&I85) -> 03/21/2026Victoria's SecretTops
A86: =IF(B86="","",ROW()-1) -> 85 | B86: T015I001 | C86: 46102 | D86: 17 | E86: Used - Excellent | F86: like new condition | G86: S | H86: =IF(B86="","",VLOOKUP(B86,Items!A:I,3,FALSE)) -> Victoria's Secret | I86: =IF(B86="","",VLOOKUP(B86,Items!A:I,9,FALSE)) -> Bottoms | J86: =IF(B86="","",TEXT(C86,"MM/DD/YYYY")&H86&I86) -> 03/21/2026Victoria's SecretBottoms
A87: =IF(B87="","",ROW()-1) -> 86 | B87: T015I002 | C87: 46103 | D87: 11 | E87: Used - Good | F87: light wear | G87: S | H87: =IF(B87="","",VLOOKUP(B87,Items!A:I,3,FALSE)) -> Ralph Lauren | I87: =IF(B87="","",VLOOKUP(B87,Items!A:I,9,FALSE)) -> Jumpsuits/Rompers | J87: =IF(B87="","",TEXT(C87,"MM/DD/YYYY")&H87&I87) -> 03/22/2026Ralph LaurenJumpsuits/Rompers
A88: =IF(B88="","",ROW()-1) -> 87 | B88: T015I005 | C88: 46106 | D88: 15 | E88: Used - Excellent | F88: like new condition | G88: S | H88: =IF(B88="","",VLOOKUP(B88,Items!A:I,3,FALSE)) -> Cotton Natural | I88: =IF(B88="","",VLOOKUP(B88,Items!A:I,9,FALSE)) -> Tops | J88: =IF(B88="","",TEXT(C88,"MM/DD/YYYY")&H88&I88) -> 03/25/2026Cotton NaturalTops
A89: =IF(B89="","",ROW()-1) | H89: =IF(B89="","",VLOOKUP(B89,Items!A:I,3,FALSE)) | I89: =IF(B89="","",VLOOKUP(B89,Items!A:I,9,FALSE)) | J89: =IF(B89="","",TEXT(C89,"MM/DD/YYYY")&H89&I89)
A90: =IF(B90="","",ROW()-1) | H90: =IF(B90="","",VLOOKUP(B90,Items!A:I,3,FALSE)) | I90: =IF(B90="","",VLOOKUP(B90,Items!A:I,9,FALSE)) | J90: =IF(B90="","",TEXT(C90,"MM/DD/YYYY")&H90&I90)
A91: =IF(B91="","",ROW()-1) | H91: =IF(B91="","",VLOOKUP(B91,Items!A:I,3,FALSE)) | I91: =IF(B91="","",VLOOKUP(B91,Items!A:I,9,FALSE)) | J91: =IF(B91="","",TEXT(C91,"MM/DD/YYYY")&H91&I91)
A92: =IF(B92="","",ROW()-1) | H92: =IF(B92="","",VLOOKUP(B92,Items!A:I,3,FALSE)) | I92: =IF(B92="","",VLOOKUP(B92,Items!A:I,9,FALSE)) | J92: =IF(B92="","",TEXT(C92,"MM/DD/YYYY")&H92&I92)
A93: =IF(B93="","",ROW()-1) | H93: =IF(B93="","",VLOOKUP(B93,Items!A:I,3,FALSE)) | I93: =IF(B93="","",VLOOKUP(B93,Items!A:I,9,FALSE)) | J93: =IF(B93="","",TEXT(C93,"MM/DD/YYYY")&H93&I93)
A94: =IF(B94="","",ROW()-1) | H94: =IF(B94="","",VLOOKUP(B94,Items!A:I,3,FALSE)) | I94: =IF(B94="","",VLOOKUP(B94,Items!A:I,9,FALSE)) | J94: =IF(B94="","",TEXT(C94,"MM/DD/YYYY")&H94&I94)
A95: =IF(B95="","",ROW()-1) | H95: =IF(B95="","",VLOOKUP(B95,Items!A:I,3,FALSE)) | I95: =IF(B95="","",VLOOKUP(B95,Items!A:I,9,FALSE)) | J95: =IF(B95="","",TEXT(C95,"MM/DD/YYYY")&H95&I95)
A96: =IF(B96="","",ROW()-1) | H96: =IF(B96="","",VLOOKUP(B96,Items!A:I,3,FALSE)) | I96: =IF(B96="","",VLOOKUP(B96,Items!A:I,9,FALSE)) | J96: =IF(B96="","",TEXT(C96,"MM/DD/YYYY")&H96&I96)
A97: =IF(B97="","",ROW()-1) | H97: =IF(B97="","",VLOOKUP(B97,Items!A:I,3,FALSE)) | I97: =IF(B97="","",VLOOKUP(B97,Items!A:I,9,FALSE)) | J97: =IF(B97="","",TEXT(C97,"MM/DD/YYYY")&H97&I97)
A98: =IF(B98="","",ROW()-1) | H98: =IF(B98="","",VLOOKUP(B98,Items!A:I,3,FALSE)) | I98: =IF(B98="","",VLOOKUP(B98,Items!A:I,9,FALSE)) | J98: =IF(B98="","",TEXT(C98,"MM/DD/YYYY")&H98&I98)
A99: =IF(B99="","",ROW()-1) | H99: =IF(B99="","",VLOOKUP(B99,Items!A:I,3,FALSE)) | I99: =IF(B99="","",VLOOKUP(B99,Items!A:I,9,FALSE)) | J99: =IF(B99="","",TEXT(C99,"MM/DD/YYYY")&H99&I99)
A100: =IF(B100="","",ROW()-1) | H100: =IF(B100="","",VLOOKUP(B100,Items!A:I,3,FALSE)) | I100: =IF(B100="","",VLOOKUP(B100,Items!A:I,9,FALSE)) | J100: =IF(B100="","",TEXT(C100,"MM/DD/YYYY")&H100&I100)
...

Sheet Sales
A1: Date of sale | B1: Time of sale | C1: Date of listing | D1: Bundle | E1: Bundle - amount of items | F1: Buyer | G1: Brand | H1: Description | I1: Size | J1: Item price | K1: Buyer shipping cost | L1: Total | M1: USPS Cost | N1: Depop fee | O1: Depop Payments fee | P1: Buyer Marketplace Fee | Q1: Boosting fee | R1: Payment type | S1: Estimated payout date | T1: Payout arrival date | U1: Category | V1: Name | W1: Address Line 1 | X1: Address Line 2 | Y1: City | Z1: State | AA1: Post Code | AB1: Country | AC1: US Sales tax | AD1: Refunded to buyer amount | AE1: Fees refunded to seller | AF1: Days_to_Sell | AG1: Alloc_Shipping | AH1: Alloc_Fees | AI1: Listing_ID
A2: 45946 | B2: 02:15 PM | C2: 45944 | D2: No | F2: kayla62 | G2: Express | H2: Express red vintage jeans in size m #minimalist #streetwear #y2k #thrift | I2: M | J2: 18 | K2: 7.99 | L2: 27.79 | M2: 0 | N2: 0 | O2: 1.42 | P2: 1.8 | R2: STRIPE | S2: 45948 | T2: 45950 | U2: Bottoms | V2: Colleen Nguyen | W2: 05641 Robin Port | Y2: Jasonfort | Z2: CO | AA2: 52357 | AB2: US | AF2: =IF(OR(A2="",C2=""),"",A2-C2) -> 2 | AG2: =IF(A2="","",IF(D2="No",IFERROR(K2*1,0),IF(D2="Yes",IFERROR(K2/E2,0),""))) -> 7.99 | AH2: =IF(A2="","",IFERROR(N2*1,0)+IFERROR(O2*1,0)+IFERROR(P2*1,0)+IFERROR(Q2*1,0)) -> 3.22 | AI2: {=IF(A2="","",IFERROR(INDEX(Listings!A:A,MATCH(TEXT(C2,"MM/DD/YYYY")&G2&U2,Listings!J$2:J$201,0)+1),""))} -> 6
A3: 45948 | B3: 06:35 PM | C3: 45942 | D3: No | F3: david_nielsen | G3: J.Crew | H3: J.Crew navy sunglasses in size s/m #aesthetic #grunge #thrift #boho #vintage | I3: S/M | J3: 15 | K3: 11.99 | L3: 28.49 | M3: 0 | N3: 0 | O3: 1.19 | P3: 1.5 | R3: STRIPE | S3: 45950 | T3: 45953 | U3: Accessories | V3: Andrew Stevens | W3: 495 Janet Cape | Y3: Port Keith | Z3: MI | AA3: 10959 | AB3: US | AF3: =IF(OR(A3="",C3=""),"",A3-C3) -> 6 | AG3: =IF(A3="","",IF(D3="No",IFERROR(K3*1,0),IF(D3="Yes",IFERROR(K3/E3,0),""))) -> 11.99 | AH3: =IF(A3="","",IFERROR(N3*1,0)+IFERROR(O3*1,0)+IFERROR(P3*1,0)+IFERROR(Q3*1,0)) -> 2.69 | AI3: {=IF(A3="","",IFERROR(INDEX(Listings!A:A,MATCH(TEXT(C3,"MM/DD/YYYY")&G3&U3,Listings!J$2:J$201,0)+1),""))} -> 4
A4: 45948 | B4: 09:22 AM | C4: 45943 | D4: No | F4: shawn_flowers | G4: H&M | H4: H&M striped denim tank top in size l #retro #minimalist #boho #thrift | I4: L | J4: 15 | K4: 11.99 | L4: 28.49 | M4: 0 | N4: 0 | O4: 1.19 | P4: 1.5 | R4: STRIPE | S4: 45950 | T4: 45953 | U4: Tops | V4: Sharon James | W4: 5341 Amanda Gardens | Y4: South Noah | Z4: AL | AA4: 84387 | AB4: US | AC4: 0.78 | AF4: =IF(OR(A4="",C4=""),"",A4-C4) -> 5 | AG4: =IF(A4="","",IF(D4="No",IFERROR(K4*1,0),IF(D4="Yes",IFERROR(K4/E4,0),""))) -> 11.99 | AH4: =IF(A4="","",IFERROR(N4*1,0)+IFERROR(O4*1,0)+IFERROR(P4*1,0)+IFERROR(Q4*1,0)) -> 2.69 | AI4: {=IF(A4="","",IFERROR(INDEX(Listings!A:A,MATCH(TEXT(C4,"MM/DD/YYYY")&G4&U4,Listings!J$2:J$201,0)+1),""))} -> 5
A5: 45950 | B5: 12:26 PM | C5: 45949 | D5: No | F5: styledonald | G5: BKE | H5: BKE striped boho tank top in size s #cottagecore #vintage #y2k #casual | I5: S | J5: 21.6 | K5: 6.49 | L5: 30.25 | M5: 0 | N5: 0 | O5: 1.71 | P5: 2.16 | R5: STRIPE | S5: 45952 | T5: 45955 | U5: Tops | V5: Maria Thomas | W5: 969 Cox Dam Suite 101 | Y5: Lake Ernest | Z5: CO | AA5: 89693 | AB5: US | AF5: =IF(OR(A5="",C5=""),"",A5-C5) -> 1 | AG5: =IF(A5="","",IF(D5="No",IFERROR(K5*1,0),IF(D5="Yes",IFERROR(K5/E5,0),""))) -> 6.49 | AH5: =IF(A5="","",IFERROR(N5*1,0)+IFERROR(O5*1,0)+IFERROR(P5*1,0)+IFERROR(Q5*1,0)) -> 3.87 | AI5: {=IF(A5="","",IFERROR(INDEX(Listings!A:A,MATCH(TEXT(C5,"MM/DD/YYYY")&G5&U5,Listings!J$2:J$201,0)+1),""))} -> 8
A6: 45952 | B6: 03:39 PM | C6: 45941 | D6: No | F6: stylerobert | G6: Deb | H6: Deb plaid cotton jeans in size s #minimalist #preppy #streetwear | I6: S | J6: 29 | K6: 4.99 | L6: 36.89 | M6: 0 | N6: 0 | O6: 2.29 | P6: 2.9 | R6: STRIPE | S6: 45954 | T6: 45957 | U6: Bottoms | V6: Michelle Miles | W6: 402 Peterson Drives Apt. 511 | Y6: Davisstad | Z6: MO | AA6: 79632 | AB6: US | AF6: =IF(OR(A6="",C6=""),"",A6-C6) -> 11 | AG6: =IF(A6="","",IF(D6="No",IFERROR(K6*1,0),IF(D6="Yes",IFERROR(K6/E6,0),""))) -> 4.99 | AH6: =IF(A6="","",IFERROR(N6*1,0)+IFERROR(O6*1,0)+IFERROR(P6*1,0)+IFERROR(Q6*1,0)) -> 5.19 | AI6: {=IF(A6="","",IFERROR(INDEX(Listings!A:A,MATCH(TEXT(C6,"MM/DD/YYYY")&G6&U6,Listings!J$2:J$201,0)+1),""))} -> 3
A7: 45955 | B7: 08:58 AM | C7: 45951 | D7: No | F7: wendystyle | G7: Zara | H7: Zara green joggers in size s #minimalist #boho #vintage | I7: S | J7: 10.5 | K7: 6.49 | L7: 18.04 | M7: 0 | N7: 0 | O7: 0.83 | P7: 1.05 | R7: STRIPE | S7: 45957 | T7: 45959 | U7: Bottoms | V7: Arthur James | W7: 018 Mack Junctions Apt. 462 | Y7: Smithview | Z7: IA | AA7: 66113 | AB7: US | AC7: 1.05 | AF7: =IF(OR(A7="",C7=""),"",A7-C7) -> 4 | AG7: =IF(A7="","",IF(D7="No",IFERROR(K7*1,0),IF(D7="Yes",IFERROR(K7/E7,0),""))) -> 6.49 | AH7: =IF(A7="","",IFERROR(N7*1,0)+IFERROR(O7*1,0)+IFERROR(P7*1,0)+IFERROR(Q7*1,0)) -> 1.88 | AI7: {=IF(A7="","",IFERROR(INDEX(Listings!A:A,MATCH(TEXT(C7,"MM/DD/YYYY")&G7&U7,Listings!J$2:J$201,0)+1),""))} -> 10
A8: 45956 | B8: 10:59 AM | C8: 45955 | D8: No | F8: colleenski | G8: Other | H8: Other black denim blouse in size s #boho #sustainable #y2k #grunge #thrift | I8: S | J8: 9.1 | K8: 5.99 | L8: 16 | M8: 0 | N8: 0 | O8: 0.72 | P8: 0.91 | R8: STRIPE | S8: 45958 | T8: 45961 | U8: Tops | V8: Katie Rodriguez | W8: 52880 Burns Creek | Y8: Natashaport | Z8: CO | AA8: 31886 | AB8: US | AC8: 0.63 | AF8: =IF(OR(A8="",C8=""),"",A8-C8) -> 1 | AG8: =IF(A8="","",IF(D8="No",IFERROR(K8*1,0),IF(D8="Yes",IFERROR(K8/E8,0),""))) -> 5.99 | AH8: =IF(A8="","",IFERROR(N8*1,0)+IFERROR(O8*1,0)+IFERROR(P8*1,0)+IFERROR(Q8*1,0)) -> 1.63 | AI8: {=IF(A8="","",IFERROR(INDEX(Listings!A:A,MATCH(TEXT(C8,"MM/DD/YYYY")&G8&U8,Listings!J$2:J$201,0)+1),""))} -> 11
A9: 45963 | B9: 08:45 AM | C9: 45939 | D9: No | F9: jeffreyfinds | G9: Levi's | H9: Levi's green flats in size 10 #streetwear #retro #grunge | I9: 10 | J9: 30 | K9: 4.99 | L9: 37.99 | M9: 0 | N9: 0 | O9: 2.37 | P9: 3 | R9: STRIPE | S9: 45965 | T9: 45969 | U9: Footwear | V9: Allison Hill | W9: 819 Johnson Course | Y9: East William | Z9: NJ | AA9: 03979 | AB9: US | AC9: 2.06 | AF9: =IF(OR(A9="",C9=""),"",A9-C9) -> 24 | AG9: =IF(A9="","",IF(D9="No",IFERROR(K9*1,0),IF(D9="Yes",IFERROR(K9/E9,0),""))) -> 4.99 | AH9: =IF(A9="","",IFERROR(N9*1,0)+IFERROR(O9*1,0)+IFERROR(P9*1,0)+IFERROR(Q9*1,0)) -> 5.37 | AI9: {=IF(A9="","",IFERROR(INDEX(Listings!A:A,MATCH(TEXT(C9,"MM/DD/YYYY")&G9&U9,Listings!J$2:J$201,0)+1),""))} -> 2
A10: 45966 | B10: 03:21 PM | C10: 45962 | D10: No | F10: vintagejohn | G10: SO Clothing | H10: SO Clothing brown bodycon dress in size xs #cottagecore #y2k | I10: XS | J10: 28 | K10: 11.99 | L10: 42.79 | M10: 0 | N10: 0 | O10: 2.21 | P10: 2.8 | R10: STRIPE | S10: 45968 | T10: 45972 | U10: Dresses | V10: Shannon Jones | W10: 82997 Kristen Valley Suite 311 | Y10: Gomezchester | Z10: CA | AA10: 61714 | AB10: US | AF10: =IF(OR(A10="",C10=""),"",A10-C10) -> 4 | AG10: =IF(A10="","",IF(D10="No",IFERROR(K10*1,0),IF(D10="Yes",IFERROR(K10/E10,0),""))) -> 11.99 | AH10: =IF(A10="","",IFERROR(N10*1,0)+IFERROR(O10*1,0)+IFERROR(P10*1,0)+IFERROR(Q10*1,0)) -> 5.01 | AI10: {=IF(A10="","",IFERROR(INDEX(Listings!A:A,MATCH(TEXT(C10,"MM/DD/YYYY")&G10&U10,Listings!J$2:J$201,0)+1),""))} -> 15
A11: 45966 | B11: 06:26 PM | C11: 45963 | D11: No | F11: melissagar | G11: Adidas | H11: Adidas coral long sleeve boho shirt in size l #retro #streetwear | I11: L | J11: 4.5 | K11: 6.49 | L11: 11.44 | M11: 0 | N11: 0 | O11: 0.36 | P11: 0.45 | R11: STRIPE | S11: 45968 | T11: 45972 | U11: Tops | V11: Angela Morton | W11: 32677 Michelle Circle | Y11: South Aaron | Z11: KY | AA11: 51674 | AB11: US | AC11: 0.24 | AF11: =IF(OR(A11="",C11=""),"",A11-C11) -> 3 | AG11: =IF(A11="","",IF(D11="No",IFERROR(K11*1,0),IF(D11="Yes",IFERROR(K11/E11,0),""))) -> 6.49 | AH11: =IF(A11="","",IFERROR(N11*1,0)+IFERROR(O11*1,0)+IFERROR(P11*1,0)+IFERROR(Q11*1,0)) -> 0.81 | AI11: {=IF(A11="","",IFERROR(INDEX(Listings!A:A,MATCH(TEXT(C11,"MM/DD/YYYY")&G11&U11,Listings!J$2:J$201,0)+1),""))} -> 17
A12: 45971 | B12: 12:25 PM | C12: 45962 | D12: No | F12: styledebbie | G12: Apt. 9 | H12: Apt. 9 brown boho romper in size xs #sustainable #thrift #streetwear | I12: XS | J12: 10.8 | K12: 11.99 | L12: 23.87 | M12: 0 | N12: 0 | O12: 0.85 | P12: 1.08 | R12: STRIPE | S12: 45973 | T12: 45976 | U12: Jumpsuits/Rompers | V12: Amy Valdez | W12: 5133 Amanda Dam | Y12: Whitemouth | Z12: SC | AA12: 33243 | AB12: US | AF12: =IF(OR(A12="",C12=""),"",A12-C12) -> 9 | AG12: =IF(A12="","",IF(D12="No",IFERROR(K12*1,0),IF(D12="Yes",IFERROR(K12/E12,0),""))) -> 11.99 | AH12: =IF(A12="","",IFERROR(N12*1,0)+IFERROR(O12*1,0)+IFERROR(P12*1,0)+IFERROR(Q12*1,0)) -> 1.93 | AI12: {=IF(A12="","",IFERROR(INDEX(Listings!A:A,MATCH(TEXT(C12,"MM/DD/YYYY")&G12&U12,Listings!J$2:J$201,0)+1),""))} -> 16
A13: 45975 | B13: 06:04 PM | C13: 45965 | D13: No | F13: rodney_bernard | G13: Levi's | H13: Levi's pink cotton dress in size m #thrift #grunge #retro | I13: M | J13: 19.5 | K13: 3.99 | L13: 25.44 | M13: 0 | N13: 0 | O13: 1.54 | P13: 1.95 | R13: STRIPE | S13: 45977 | T13: 45979 | U13: Dresses | V13: Richard Gibson | W13: 34309 Julie Centers Apt. 978 | Y13: North Susan | Z13: OR | AA13: 11001 | AB13: US | AC13: 1.37 | AF13: =IF(OR(A13="",C13=""),"",A13-C13) -> 10 | AG13: =IF(A13="","",IF(D13="No",IFERROR(K13*1,0),IF(D13="Yes",IFERROR(K13/E13,0),""))) -> 3.99 | AH13: =IF(A13="","",IFERROR(N13*1,0)+IFERROR(O13*1,0)+IFERROR(P13*1,0)+IFERROR(Q13*1,0)) -> 3.49 | AI13: {=IF(A13="","",IFERROR(INDEX(Listings!A:A,MATCH(TEXT(C13,"MM/DD/YYYY")&G13&U13,Listings!J$2:J$201,0)+1),""))} -> 18
A14: 45975 | B14: 01:45 PM | C14: 45966 | D14: No | F14: michelle_powell | G14: Victoria's Secret | H14: Victoria's Secret green oversized cami in size m #streetwear #casual #vintage #retro #preppy | I14: M | J14: 19 | K14: 3.99 | L14: 24.89 | M14: 0 | N14: 0 | O14: 1.5 | P14: 1.9 | R14: STRIPE | S14: 45977 | T14: 45981 | U14: Tops | V14: Andrea Jones | W14: 909 Robert Prairie | Y14: Sarahborough | Z14: MA | AA14: 88283 | AB14: US | AC14: 1.28 | AF14: =IF(OR(A14="",C14=""),"",A14-C14) -> 9 | AG14: =IF(A14="","",IF(D14="No",IFERROR(K14*1,0),IF(D14="Yes",IFERROR(K14/E14,0),""))) -> 3.99 | AH14: =IF(A14="","",IFERROR(N14*1,0)+IFERROR(O14*1,0)+IFERROR(P14*1,0)+IFERROR(Q14*1,0)) -> 3.4 | AI14: {=IF(A14="","",IFERROR(INDEX(Listings!A:A,MATCH(TEXT(C14,"MM/DD/YYYY")&G14&U14,Listings!J$2:J$201,0)+1),""))} -> 20
A15: 45977 | B15: 03:45 PM | C15: 45961 | D15: No | F15: christophertuc | G15: Gap | H15: Gap plaid bodycon dress in size m #casual #cottagecore #aesthetic | I15: M | J15: 40 | K15: 11.99 | L15: 55.99 | M15: 0 | N15: 0 | O15: 3.16 | P15: 4 | R15: STRIPE | S15: 45979 | T15: 45982 | U15: Dresses | V15: Shawn Arroyo | W15: 227 Joseph Well | Y15: Brandtside | Z15: KY | AA15: 99495 | AB15: US | AF15: =IF(OR(A15="",C15=""),"",A15-C15) -> 16 | AG15: =IF(A15="","",IF(D15="No",IFERROR(K15*1,0),IF(D15="Yes",IFERROR(K15/E15,0),""))) -> 11.99 | AH15: =IF(A15="","",IFERROR(N15*1,0)+IFERROR(O15*1,0)+IFERROR(P15*1,0)+IFERROR(Q15*1,0)) -> 7.16 | AI15: {=IF(A15="","",IFERROR(INDEX(Listings!A:A,MATCH(TEXT(C15,"MM/DD/YYYY")&G15&U15,Listings!J$2:J$201,0)+1),""))} -> 13
A16: 45980 | B16: 11:20 PM | C16: 45961 | D16: No | F16: wandasan | G16: J.Crew | H16: J.Crew white mini dress in size l #boho #aesthetic | I16: L | J16: 25 | K16: 11.99 | L16: 39.49 | M16: 0 | N16: 0 | O16: 1.98 | P16: 2.5 | R16: STRIPE | S16: 45982 | T16: 45984 | U16: Dresses | V16: Christina Collins | W16: 713 Caleb Brooks Apt. 930 | Y16: Lake Crystalbury | Z16: PA | AA16: 09335 | AB16: US | AC16: 1.72 | AF16: =IF(OR(A16="",C16=""),"",A16-C16) -> 19 | AG16: =IF(A16="","",IF(D16="No",IFERROR(K16*1,0),IF(D16="Yes",IFERROR(K16/E16,0),""))) -> 11.99 | AH16: =IF(A16="","",IFERROR(N16*1,0)+IFERROR(O16*1,0)+IFERROR(P16*1,0)+IFERROR(Q16*1,0)) -> 4.48 | AI16: {=IF(A16="","",IFERROR(INDEX(Listings!A:A,MATCH(TEXT(C16,"MM/DD/YYYY")&G16&U16,Listings!J$2:J$201,0)+1),""))} -> 14
A17: 45984 | B17: 04:46 PM | C17: 45970 | D17: No | F17: emily15 | G17: Free People | H17: Free People purple long sleeve fitted shirt in size s #grunge #minimalist #y2k #retro #vintage | I17: S | J17: 20 | K17: 5.99 | L17: 27.99 | M17: 0 | N17: 0 | O17: 1.58 | P17: 2 | R17: STRIPE | S17: 45986 | T17: 45988 | U17: Tops | V17: Cynthia Foster | W17: 5107 Charles Forest Suite 251 | Y17: West Justin | Z17: AL | AA17: 57934 | AB17: US | AF17: =IF(OR(A17="",C17=""),"",A17-C17) -> 14 | AG17: =IF(A17="","",IF(D17="No",IFERROR(K17*1,0),IF(D17="Yes",IFERROR(K17/E17,0),""))) -> 5.99 | AH17: =IF(A17="","",IFERROR(N17*1,0)+IFERROR(O17*1,0)+IFERROR(P17*1,0)+IFERROR(Q17*1,0)) -> 3.58 | AI17: {=IF(A17="","",IFERROR(INDEX(Listings!A:A,MATCH(TEXT(C17,"MM/DD/YYYY")&G17&U17,Listings!J$2:J$201,0)+1),""))} -> 21
A18: 45993 | B18: 06:07 PM | C18: 45990 | D18: No | F18: josephfre | G18: H&M | H18: H&M coral sundress in size s #preppy #vintage | I18: S | J18: 30 | K18: 7.99 | L18: 40.99 | M18: 0 | N18: 0 | O18: 2.37 | P18: 3 | R18: STRIPE | S18: 45995 | T18: 45998 | U18: Dresses | V18: Christina Walters | W18: 64005 Dana Greens | Y18: Lake Scott | Z18: IN | AA18: 92994 | AB18: US | AF18: =IF(OR(A18="",C18=""),"",A18-C18) -> 3 | AG18: =IF(A18="","",IF(D18="No",IFERROR(K18*1,0),IF(D18="Yes",IFERROR(K18/E18,0),""))) -> 7.99 | AH18: =IF(A18="","",IFERROR(N18*1,0)+IFERROR(O18*1,0)+IFERROR(P18*1,0)+IFERROR(Q18*1,0)) -> 5.37 | AI18: {=IF(A18="","",IFERROR(INDEX(Listings!A:A,MATCH(TEXT(C18,"MM/DD/YYYY")&G18&U18,Listings!J$2:J$201,0)+1),""))} -> 25
A19: 45996 | B19: 09:59 AM | C19: 45971 | D19: No | F19: vanessafinds | G19: SO Clothing | H19: SO Clothing white wide leg pants in size m #streetwear #aesthetic #minimalist #y2k #retro | I19: M | J19: 22 | K19: 5.99 | L19: 30.19 | M19: 0 | N19: 0 | O19: 1.74 | P19: 2.2 | R19: STRIPE | S19: 45998 | T19: 46001 | U19: Bottoms | V19: Michele Carr | W19: 841 Joseph Coves | Y19: West Juan | Z19: PA | AA19: 28108 | AB19: US | AC19: 1.89 | AF19: =IF(OR(A19="",C19=""),"",A19-C19) -> 25 | AG19: =IF(A19="","",IF(D19="No",IFERROR(K19*1,0),IF(D19="Yes",IFERROR(K19/E19,0),""))) -> 5.99 | AH19: =IF(A19="","",IFERROR(N19*1,0)+IFERROR(O19*1,0)+IFERROR(P19*1,0)+IFERROR(Q19*1,0)) -> 3.94 | AI19: {=IF(A19="","",IFERROR(INDEX(Listings!A:A,MATCH(TEXT(C19,"MM/DD/YYYY")&G19&U19,Listings!J$2:J$201,0)+1),""))} -> 22
A20: 46024 | B20: 05:15 PM | C20: 46012 | D20: No | F20: stylegregory | G20: Victoria's Secret | H20: Victoria's Secret blue one-piece swimsuit in size m #retro #casual | I20: M | J20: 15 | K20: 4.99 | L20: 21.49 | M20: 0 | N20: 0 | O20: 1.19 | P20: 1.5 | R20: STRIPE | S20: 46026 | T20: 46030 | U20: Swimwear | V20: Ashley Waller | W20: 19655 Obrien Pass Apt. 693 | Y20: Bradleychester | Z20: IN | AA20: 00722 | AB20: US | AF20: =IF(OR(A20="",C20=""),"",A20-C20) -> 12 | AG20: =IF(A20="","",IF(D20="No",IFERROR(K20*1,0),IF(D20="Yes",IFERROR(K20/E20,0),""))) -> 4.99 | AH20: =IF(A20="","",IFERROR(N20*1,0)+IFERROR(O20*1,0)+IFERROR(P20*1,0)+IFERROR(Q20*1,0)) -> 2.69 | AI20: {=IF(A20="","",IFERROR(INDEX(Listings!A:A,MATCH(TEXT(C20,"MM/DD/YYYY")&G20&U20,Listings!J$2:J$201,0)+1),""))} -> 30
A21: 46025 | B21: 12:48 PM | C21: 46019 | D21: No | F21: robertshop | G21: BKE | H21: BKE cream lace sweater in size s #aesthetic #retro #minimalist #thrift #preppy | I21: S | J21: 21 | K21: 4.99 | L21: 28.09 | M21: 0 | N21: 0 | O21: 1.66 | P21: 2.1 | R21: STRIPE | S21: 46027 | T21: 46029 | U21: Tops | V21: Edward Martinez | W21: 299 Sullivan Village Apt. 443 | Y21: Floydmouth | Z21: MI | AA21: 61447 | AB21: US | AC21: 1.02 | AF21: =IF(OR(A21="",C21=""),"",A21-C21) -> 6 | AG21: =IF(A21="","",IF(D21="No",IFERROR(K21*1,0),IF(D21="Yes",IFERROR(K21/E21,0),""))) -> 4.99 | AH21: =IF(A21="","",IFERROR(N21*1,0)+IFERROR(O21*1,0)+IFERROR(P21*1,0)+IFERROR(Q21*1,0)) -> 3.76 | AI21: {=IF(A21="","",IFERROR(INDEX(Listings!A:A,MATCH(TEXT(C21,"MM/DD/YYYY")&G21&U21,Listings!J$2:J$201,0)+1),""))} -> 37
A22: 46025 | B22: 01:21 PM | C22: 46020 | D22: No | F22: laura44 | G22: American Eagle | H22: American Eagle teal boho bikini top in size m #cottagecore #casual #minimalist #vintage #y2k | I22: M | J22: 9 | K22: 6.49 | L22: 16.39 | M22: 0 | N22: 0 | O22: 0.71 | P22: 0.9 | R22: STRIPE | S22: 46027 | T22: 46030 | U22: Swimwear | V22: Michael Dixon | W22: 148 Davis Terrace | Y22: Lake Lance | Z22: NY | AA22: 26601 | AB22: US | AC22: 0.81 | AF22: =IF(OR(A22="",C22=""),"",A22-C22) -> 5 | AG22: =IF(A22="","",IF(D22="No",IFERROR(K22*1,0),IF(D22="Yes",IFERROR(K22/E22,0),""))) -> 6.49 | AH22: =IF(A22="","",IFERROR(N22*1,0)+IFERROR(O22*1,0)+IFERROR(P22*1,0)+IFERROR(Q22*1,0)) -> 1.61 | AI22: {=IF(A22="","",IFERROR(INDEX(Listings!A:A,MATCH(TEXT(C22,"MM/DD/YYYY")&G22&U22,Listings!J$2:J$201,0)+1),""))} -> 38
A23: 46026 | B23: 08:15 AM | C23: 46012 | D23: No | F23: lisa27 | G23: Adidas | H23: Adidas pink sundress in size m #sustainable #minimalist #casual #grunge | I23: M | J23: 28.9 | K23: 6.49 | L23: 38.28 | M23: 0 | N23: 0 | O23: 2.28 | P23: 2.89 | R23: STRIPE | S23: 46028 | T23: 46031 | U23: Dresses | V23: Shannon Walker | W23: 4330 Raymond Harbors Apt. 458 | Y23: Frazierside | Z23: GA | AA23: 43905 | AB23: US | AC23: 2.46 | AF23: =IF(OR(A23="",C23=""),"",A23-C23) -> 14 | AG23: =IF(A23="","",IF(D23="No",IFERROR(K23*1,0),IF(D23="Yes",IFERROR(K23/E23,0),""))) -> 6.49 | AH23: =IF(A23="","",IFERROR(N23*1,0)+IFERROR(O23*1,0)+IFERROR(P23*1,0)+IFERROR(Q23*1,0)) -> 5.17 | AI23: {=IF(A23="","",IFERROR(INDEX(Listings!A:A,MATCH(TEXT(C23,"MM/DD/YYYY")&G23&U23,Listings!J$2:J$201,0)+1),""))} -> 31
A24: 46026 | B24: 01:30 PM | C24: 46022 | D24: No | F24: cherylmac | G24: Hollister | H24: Hollister burgundy fitted tank top in size l #minimalist #streetwear | I24: L | J24: 20 | K24: 5.99 | L24: 27.99 | M24: 0 | N24: 0 | O24: 1.58 | P24: 2 | R24: STRIPE | S24: 46028 | T24: 46031 | U24: Tops | V24: Angel Riggs | W24: 9367 Sanchez Shoal Apt. 163 | Y24: Port Susan | Z24: IA | AA24: 68390 | AB24: US | AD24: 27.99 | AE24: 3.58 | AF24: =IF(OR(A24="",C24=""),"",A24-C24) -> 4 | AG24: =IF(A24="","",IF(D24="No",IFERROR(K24*1,0),IF(D24="Yes",IFERROR(K24/E24,0),""))) -> 5.99 | AH24: =IF(A24="","",IFERROR(N24*1,0)+IFERROR(O24*1,0)+IFERROR(P24*1,0)+IFERROR(Q24*1,0)) -> 3.58 | AI24: {=IF(A24="","",IFERROR(INDEX(Listings!A:A,MATCH(TEXT(C24,"MM/DD/YYYY")&G24&U24,Listings!J$2:J$201,0)+1),""))} -> 39
A25: 46027 | B25: 09:43 PM | C25: 45992 | D25: No | F25: vintagenicole | G25: Tommy Hilfiger | H25: Tommy Hilfiger navy denim cami in size xs #sustainable #minimalist #y2k #vintage | I25: XS | J25: 12.6 | K25: 6.49 | L25: 20.35 | M25: 0 | N25: 0 | O25: 1 | P25: 1.26 | R25: STRIPE | S25: 46029 | T25: 46033 | U25: Tops | V25: Adam Jones | W25: 059 Russell Canyon | Y25: Michaelton | Z25: WA | AA25: 47399 | AB25: US | AC25: 0.69 | AF25: =IF(OR(A25="",C25=""),"",A25-C25) -> 35 | AG25: =IF(A25="","",IF(D25="No",IFERROR(K25*1,0),IF(D25="Yes",IFERROR(K25/E25,0),""))) -> 6.49 | AH25: =IF(A25="","",IFERROR(N25*1,0)+IFERROR(O25*1,0)+IFERROR(P25*1,0)+IFERROR(Q25*1,0)) -> 2.26 | AI25: {=IF(A25="","",IFERROR(INDEX(Listings!A:A,MATCH(TEXT(C25,"MM/DD/YYYY")&G25&U25,Listings!J$2:J$201,0)+1),""))} -> 27
A26: 46028 | B26: 08:39 PM | C26: 46009 | D26: No | F26: kimberly_henson | G26: Express | H26: Express navy button-down shirt in size s #streetwear #casual | I26: S | J26: 5.95 | K26: 3.99 | L26: 10.54 | M26: 0 | N26: 0 | O26: 0.47 | P26: 0.6 | R26: STRIPE | S26: 46030 | T26: 46032 | U26: Tops | V26: David Garcia | W26: 232 Nicole Burg Apt. 563 | Y26: Erikville | Z26: OH | AA26: 50641 | AB26: US | AF26: =IF(OR(A26="",C26=""),"",A26-C26) -> 19 | AG26: =IF(A26="","",IF(D26="No",IFERROR(K26*1,0),IF(D26="Yes",IFERROR(K26/E26,0),""))) -> 3.99 | AH26: =IF(A26="","",IFERROR(N26*1,0)+IFERROR(O26*1,0)+IFERROR(P26*1,0)+IFERROR(Q26*1,0)) -> 1.07 | AI26: {=IF(A26="","",IFERROR(INDEX(Listings!A:A,MATCH(TEXT(C26,"MM/DD/YYYY")&G26&U26,Listings!J$2:J$201,0)+1),""))} -> 29
A27: 46032 | B27: 07:26 AM | C27: 46031 | D27: No | F27: elizabeth_miller | G27: Zara | H27: Zara red cropped oversized top in size s #grunge #vintage #casual #cottagecore #streetwear | I27: S | J27: 18 | K27: 11.99 | L27: 31.79 | M27: 0 | N27: 0 | O27: 1.42 | P27: 1.8 | R27: STRIPE | S27: 46034 | T27: 46036 | U27: Tops | V27: Ms. Susan Vargas | W27: 72046 Lewis Islands Suite 646 | Y27: Maryfort | Z27: NY | AA27: 03041 | AB27: US | AC27: 0.73 | AF27: =IF(OR(A27="",C27=""),"",A27-C27) -> 1 | AG27: =IF(A27="","",IF(D27="No",IFERROR(K27*1,0),IF(D27="Yes",IFERROR(K27/E27,0),""))) -> 11.99 | AH27: =IF(A27="","",IFERROR(N27*1,0)+IFERROR(O27*1,0)+IFERROR(P27*1,0)+IFERROR(Q27*1,0)) -> 3.22 | AI27: {=IF(A27="","",IFERROR(INDEX(Listings!A:A,MATCH(TEXT(C27,"MM/DD/YYYY")&G27&U27,Listings!J$2:J$201,0)+1),""))} -> 45
A28: 46037 | B28: 12:40 PM | C28: 46015 | D28: No | F28: shelbywear | G28: H&M | H28: H&M olive swim cover-up in size m #minimalist #aesthetic #preppy #thrift | I28: M | J28: 7.2 | K28: 7.99 | L28: 15.91 | M28: 0 | N28: 0 | O28: 0.57 | P28: 0.72 | R28: STRIPE | S28: 46039 | T28: 46042 | U28: Swimwear | V28: Renee Mcdaniel | W28: 6159 Alvarado Crossing | Y28: Williamchester | Z28: TX | AA28: 43254 | AB28: US | AC28: 0.69 | AF28: =IF(OR(A28="",C28=""),"",A28-C28) -> 22 | AG28: =IF(A28="","",IF(D28="No",IFERROR(K28*1,0),IF(D28="Yes",IFERROR(K28/E28,0),""))) -> 7.99 | AH28: =IF(A28="","",IFERROR(N28*1,0)+IFERROR(O28*1,0)+IFERROR(P28*1,0)+IFERROR(Q28*1,0)) -> 1.29 | AI28: {=IF(A28="","",IFERROR(INDEX(Listings!A:A,MATCH(TEXT(C28,"MM/DD/YYYY")&G28&U28,Listings!J$2:J$201,0)+1),""))} -> 34
A29: 46039 | B29: 06:10 PM | C29: 46030 | D29: No | F29: jeffrey77 | G29: J.Crew | H29: J.Crew white cotton top in size l #y2k #cottagecore | I29: L | J29: 23 | K29: 7.99 | L29: 33.29 | M29: 0 | N29: 0 | O29: 1.82 | P29: 2.3 | R29: STRIPE | S29: 46041 | T29: 46044 | U29: Tops | V29: Kimberly Morrison | W29: 6706 Caldwell Union | Y29: Ramseymouth | Z29: PA | AA29: 17229 | AB29: US | AC29: 1.67 | AF29: =IF(OR(A29="",C29=""),"",A29-C29) -> 9 | AG29: =IF(A29="","",IF(D29="No",IFERROR(K29*1,0),IF(D29="Yes",IFERROR(K29/E29,0),""))) -> 7.99 | AH29: =IF(A29="","",IFERROR(N29*1,0)+IFERROR(O29*1,0)+IFERROR(P29*1,0)+IFERROR(Q29*1,0)) -> 4.12 | AI29: {=IF(A29="","",IFERROR(INDEX(Listings!A:A,MATCH(TEXT(C29,"MM/DD/YYYY")&G29&U29,Listings!J$2:J$201,0)+1),""))} -> 44
A30: 46041 | B30: 05:58 PM | C30: 46024 | D30: No | F30: jonathonwri | G30: Gap | H30: Gap burgundy wide leg pants in size s #boho #retro | I30: S | J30: 22 | K30: 5.99 | L30: 30.19 | M30: 0 | N30: 0 | O30: 1.74 | P30: 2.2 | R30: STRIPE | S30: 46043 | T30: 46046 | U30: Bottoms | V30: Natasha Wells | W30: 734 Jones Heights Apt. 455 | Y30: East Edwardfurt | Z30: TX | AA30: 91458 | AB30: US | AC30: 1.17 | AF30: =IF(OR(A30="",C30=""),"",A30-C30) -> 17 | AG30: =IF(A30="","",IF(D30="No",IFERROR(K30*1,0),IF(D30="Yes",IFERROR(K30/E30,0),""))) -> 5.99 | AH30: =IF(A30="","",IFERROR(N30*1,0)+IFERROR(O30*1,0)+IFERROR(P30*1,0)+IFERROR(Q30*1,0)) -> 3.94 | AI30: {=IF(A30="","",IFERROR(INDEX(Listings!A:A,MATCH(TEXT(C30,"MM/DD/YYYY")&G30&U30,Listings!J$2:J$201,0)+1),""))} -> 42
A31: 46045 | B31: 06:17 PM | C31: 46035 | D31: No | F31: jonathanwoo | G31: Zara | H31: Zara navy fitted sweater in size s #cottagecore #y2k #preppy #vintage | I31: S | J31: 12.75 | K31: 3.99 | L31: 18.02 | M31: 0 | N31: 0 | O31: 1.01 | P31: 1.28 | R31: STRIPE | S31: 46047 | T31: 46050 | U31: Tops | V31: Travis Marshall | W31: 41904 Sanders Stravenue | Y31: North Brittany | Z31: WA | AA31: 82714 | AB31: US | AC31: 0.7 | AF31: =IF(OR(A31="",C31=""),"",A31-C31) -> 10 | AG31: =IF(A31="","",IF(D31="No",IFERROR(K31*1,0),IF(D31="Yes",IFERROR(K31/E31,0),""))) -> 3.99 | AH31: =IF(A31="","",IFERROR(N31*1,0)+IFERROR(O31*1,0)+IFERROR(P31*1,0)+IFERROR(Q31*1,0)) -> 2.29 | AI31: {=IF(A31="","",IFERROR(INDEX(Listings!A:A,MATCH(TEXT(C31,"MM/DD/YYYY")&G31&U31,Listings!J$2:J$201,0)+1),""))} -> 49
A32: 46046 | B32: 01:25 PM | C32: 46022 | D32: Yes | E32: 2 | F32: davidwear | G32: The North Face | H32: The North Face navy wide leg pants in size l #boho #preppy #grunge #retro | I32: L | J32: 18.75 | K32: 7.99 | L32: 51.39 | M32: 0 | N32: 0 | O32: 3.12 | P32: 3.95 | R32: STRIPE | S32: 46048 | T32: 46051 | U32: Bottoms | V32: Justin Lowery | W32: 8895 Salazar Stravenue | Y32: Rivasside | Z32: LA | AA32: 58947 | AB32: US | AF32: =IF(OR(A32="",C32=""),"",A32-C32) -> 24 | AG32: =IF(A32="","",IF(D32="No",IFERROR(K32*1,0),IF(D32="Yes",IFERROR(K32/E32,0),""))) -> 3.995 | AH32: =IF(A32="","",IFERROR(N32*1,0)+IFERROR(O32*1,0)+IFERROR(P32*1,0)+IFERROR(Q32*1,0)) -> 7.07 | AI32: {=IF(A32="","",IFERROR(INDEX(Listings!A:A,MATCH(TEXT(C32,"MM/DD/YYYY")&G32&U32,Listings!J$2:J$201,0)+1),""))} -> 40
A33: 46046 | B33: 01:25 PM | C33: 46023 | D33: Yes | F33: davidwear | G33: Hollister | H33: Hollister burgundy graphic tee in size xs #vintage #aesthetic #boho | I33: XS | J33: 20.7 | N33: 0 | R33: STRIPE | S33: 46048 | T33: 46051 | U33: Tops | V33: Justin Lowery | W33: 8895 Salazar Stravenue | Y33: Rivasside | Z33: LA | AA33: 58947 | AB33: US | AF33: =IF(OR(A33="",C33=""),"",A33-C33) -> 23 | AG33: =IF(A33="","",IF(D33="No",IFERROR(K33*1,0),IF(D33="Yes",IFERROR(K33/E33,0),""))) -> 0 | AH33: =IF(A33="","",IFERROR(N33*1,0)+IFERROR(O33*1,0)+IFERROR(P33*1,0)+IFERROR(Q33*1,0)) -> 0 | AI33: {=IF(A33="","",IFERROR(INDEX(Listings!A:A,MATCH(TEXT(C33,"MM/DD/YYYY")&G33&U33,Listings!J$2:J$201,0)+1),""))} -> 41
A34: 46046 | B34: 07:00 AM | C34: 46032 | D34: Yes | E34: 2 | F34: thriftjeffrey | G34: Other | H34: Other purple cargo pants in size m #preppy #thrift #y2k #cottagecore #retro | I34: M | J34: 29 | K34: 6.49 | L34: 52.69 | M34: 0 | N34: 0 | O34: 3.32 | P34: 4.2 | R34: STRIPE | S34: 46048 | T34: 46050 | U34: Bottoms | V34: Amy Crane | W34: 003 Mary Road | Y34: East David | Z34: CA | AA34: 88248 | AB34: US | AC34: 1.64 | AF34: =IF(OR(A34="",C34=""),"",A34-C34) -> 14 | AG34: =IF(A34="","",IF(D34="No",IFERROR(K34*1,0),IF(D34="Yes",IFERROR(K34/E34,0),""))) -> 3.245 | AH34: =IF(A34="","",IFERROR(N34*1,0)+IFERROR(O34*1,0)+IFERROR(P34*1,0)+IFERROR(Q34*1,0)) -> 7.52 | AI34: {=IF(A34="","",IFERROR(INDEX(Listings!A:A,MATCH(TEXT(C34,"MM/DD/YYYY")&G34&U34,Listings!J$2:J$201,0)+1),""))} -> 47
A35: 46046 | B35: 07:00 AM | C35: 46033 | D35: Yes | F35: thriftjeffrey | G35: Nike | H35: Nike black ribbed bikini top in size m #y2k #grunge | I35: M | J35: 13 | N35: 0 | R35: STRIPE | S35: 46048 | T35: 46050 | U35: Swimwear | V35: Amy Crane | W35: 003 Mary Road | Y35: East David | Z35: CA | AA35: 88248 | AB35: US | AF35: =IF(OR(A35="",C35=""),"",A35-C35) -> 13 | AG35: =IF(A35="","",IF(D35="No",IFERROR(K35*1,0),IF(D35="Yes",IFERROR(K35/E35,0),""))) -> 0 | AH35: =IF(A35="","",IFERROR(N35*1,0)+IFERROR(O35*1,0)+IFERROR(P35*1,0)+IFERROR(Q35*1,0)) -> 0 | AI35: {=IF(A35="","",IFERROR(INDEX(Listings!A:A,MATCH(TEXT(C35,"MM/DD/YYYY")&G35&U35,Listings!J$2:J$201,0)+1),""))} -> 48
A36: 46046 | B36: 07:24 PM | C36: 46044 | D36: No | F36: gabriellefinds | G36: Abercrombie & Fitch | H36: Abercrombie & Fitch black bodycon dress in size s #retro #vintage | I36: S | J36: 19 | K36: 3.99 | L36: 24.89 | M36: 0 | N36: 0 | O36: 1.5 | P36: 1.9 | R36: STRIPE | S36: 46048 | T36: 46052 | U36: Dresses | V36: Michael Turner | W36: 058 Stanley Cliff | Y36: Alexanderchester | Z36: CA | AA36: 64752 | AB36: US | AC36: 0.85 | AF36: =IF(OR(A36="",C36=""),"",A36-C36) -> 2 | AG36: =IF(A36="","",IF(D36="No",IFERROR(K36*1,0),IF(D36="Yes",IFERROR(K36/E36,0),""))) -> 3.99 | AH36: =IF(A36="","",IFERROR(N36*1,0)+IFERROR(O36*1,0)+IFERROR(P36*1,0)+IFERROR(Q36*1,0)) -> 3.4 | AI36: {=IF(A36="","",IFERROR(INDEX(Listings!A:A,MATCH(TEXT(C36,"MM/DD/YYYY")&G36&U36,Listings!J$2:J$201,0)+1),""))} -> 51
A37: 46050 | B37: 10:17 PM | C37: 46046 | D37: No | F37: maria_zimmerman | G37: Urban Outfitters | H37: Urban Outfitters burgundy maxi dress in size s #thrift #grunge | I37: S | J37: 24 | K37: 3.99 | L37: 30.39 | M37: 0 | N37: 0 | O37: 1.9 | P37: 2.4 | R37: STRIPE | S37: 46052 | T37: 46056 | U37: Dresses | V37: Tyler Reid | W37: 84987 Graham Street Suite 531 | Y37: Nicolebury | Z37: IA | AA37: 98867 | AB37: US | AF37: =IF(OR(A37="",C37=""),"",A37-C37) -> 4 | AG37: =IF(A37="","",IF(D37="No",IFERROR(K37*1,0),IF(D37="Yes",IFERROR(K37/E37,0),""))) -> 3.99 | AH37: =IF(A37="","",IFERROR(N37*1,0)+IFERROR(O37*1,0)+IFERROR(P37*1,0)+IFERROR(Q37*1,0)) -> 4.3 | AI37: {=IF(A37="","",IFERROR(INDEX(Listings!A:A,MATCH(TEXT(C37,"MM/DD/YYYY")&G37&U37,Listings!J$2:J$201,0)+1),""))} -> 53
A38: 46051 | B38: 08:18 PM | C38: 46026 | D38: No | F38: mark_owens | G38: Other | H38: Other gray joggers in size xs #boho #streetwear #cottagecore #minimalist | I38: XS | J38: 18 | K38: 5.99 | L38: 25.79 | M38: 0 | N38: 0 | O38: 1.42 | P38: 1.8 | R38: STRIPE | S38: 46053 | T38: 46055 | U38: Bottoms | V38: Daniel Perry | W38: 66909 Woods Knoll | Y38: Karenchester | Z38: WA | AA38: 71046 | AB38: US | AC38: 0.99 | AF38: =IF(OR(A38="",C38=""),"",A38-C38) -> 25 | AG38: =IF(A38="","",IF(D38="No",IFERROR(K38*1,0),IF(D38="Yes",IFERROR(K38/E38,0),""))) -> 5.99 | AH38: =IF(A38="","",IFERROR(N38*1,0)+IFERROR(O38*1,0)+IFERROR(P38*1,0)+IFERROR(Q38*1,0)) -> 3.22 | AI38: {=IF(A38="","",IFERROR(INDEX(Listings!A:A,MATCH(TEXT(C38,"MM/DD/YYYY")&G38&U38,Listings!J$2:J$201,0)+1),""))} -> 43
A39: 46053 | B39: 01:37 PM | C39: 46052 | D39: No | F39: anthonyros | G39: Victoria's Secret | H39: Victoria's Secret floral denim scarf in size s #casual #aesthetic #cottagecore | I39: S | J39: 6 | K39: 11.99 | L39: 18.59 | M39: 0 | N39: 0 | O39: 0.47 | P39: 0.6 | R39: STRIPE | S39: 46055 | T39: 46058 | U39: Accessories | V39: Leonard Gray | W39: 3545 Beard Squares | Y39: Angelahaven | Z39: IA | AA39: 25543 | AB39: US | AF39: =IF(OR(A39="",C39=""),"",A39-C39) -> 1 | AG39: =IF(A39="","",IF(D39="No",IFERROR(K39*1,0),IF(D39="Yes",IFERROR(K39/E39,0),""))) -> 11.99 | AH39: =IF(A39="","",IFERROR(N39*1,0)+IFERROR(O39*1,0)+IFERROR(P39*1,0)+IFERROR(Q39*1,0)) -> 1.07 | AI39: {=IF(A39="","",IFERROR(INDEX(Listings!A:A,MATCH(TEXT(C39,"MM/DD/YYYY")&G39&U39,Listings!J$2:J$201,0)+1),""))} -> 57
A40: 46076 | B40: 09:49 AM | C40: 46062 | D40: No | F40: jeremywhi | G40: Free People | H40: Free People burgundy athletic blouse in size l #minimalist #cottagecore #thrift #aesthetic #grunge | I40: L | J40: 19 | K40: 4.99 | L40: 25.89 | M40: 0 | N40: 0 | O40: 1.5 | P40: 1.9 | R40: STRIPE | S40: 46078 | T40: 46082 | U40: Tops | V40: Brian Lee | W40: 824 Terri Plaza | Y40: Heidiberg | Z40: NY | AA40: 84107 | AB40: US | AF40: =IF(OR(A40="",C40=""),"",A40-C40) -> 14 | AG40: =IF(A40="","",IF(D40="No",IFERROR(K40*1,0),IF(D40="Yes",IFERROR(K40/E40,0),""))) -> 4.99 | AH40: =IF(A40="","",IFERROR(N40*1,0)+IFERROR(O40*1,0)+IFERROR(P40*1,0)+IFERROR(Q40*1,0)) -> 3.4 | AI40: {=IF(A40="","",IFERROR(INDEX(Listings!A:A,MATCH(TEXT(C40,"MM/DD/YYYY")&G40&U40,Listings!J$2:J$201,0)+1),""))} -> 64
A41: 46077 | B41: 09:00 AM | C41: 46070 | D41: No | F41: audreyhar | G41: Nike | H41: Nike burgundy wide leg pants in size s #thrift #aesthetic | I41: S | J41: 6.75 | K41: 6.49 | L41: 13.92 | M41: 0 | N41: 0 | O41: 0.53 | P41: 0.68 | R41: STRIPE | S41: 46079 | T41: 46082 | U41: Bottoms | V41: Katherine Salas | W41: 2047 Lynn Locks Suite 190 | Y41: East Lisa | Z41: LA | AA41: 40325 | AB41: US | AF41: =IF(OR(A41="",C41=""),"",A41-C41) -> 7 | AG41: =IF(A41="","",IF(D41="No",IFERROR(K41*1,0),IF(D41="Yes",IFERROR(K41/E41,0),""))) -> 6.49 | AH41: =IF(A41="","",IFERROR(N41*1,0)+IFERROR(O41*1,0)+IFERROR(P41*1,0)+IFERROR(Q41*1,0)) -> 1.21 | AI41: {=IF(A41="","",IFERROR(INDEX(Listings!A:A,MATCH(TEXT(C41,"MM/DD/YYYY")&G41&U41,Listings!J$2:J$201,0)+1),""))} -> 66
A42: 46079 | B42: 05:24 PM | C42: 46056 | D42: No | F42: thriftkatherine | G42: Hollister | H42: Hollister white bodycon dress in size l #aesthetic #sustainable | I42: L | J42: 32.3 | K42: 4.99 | L42: 40.52 | M42: 0 | N42: 0 | O42: 2.55 | P42: 3.23 | R42: STRIPE | S42: 46081 | T42: 46085 | U42: Dresses | V42: Nathan Freeman | W42: 770 Kelly Lodge Apt. 495 | Y42: Transtad | Z42: AL | AA42: 56272 | AB42: US | AF42: =IF(OR(A42="",C42=""),"",A42-C42) -> 23 | AG42: =IF(A42="","",IF(D42="No",IFERROR(K42*1,0),IF(D42="Yes",IFERROR(K42/E42,0),""))) -> 4.99 | AH42: =IF(A42="","",IFERROR(N42*1,0)+IFERROR(O42*1,0)+IFERROR(P42*1,0)+IFERROR(Q42*1,0)) -> 5.78 | AI42: {=IF(A42="","",IFERROR(INDEX(Listings!A:A,MATCH(TEXT(C42,"MM/DD/YYYY")&G42&U42,Listings!J$2:J$201,0)+1),""))} -> 59
A43: 46079 | B43: 05:38 PM | C43: 46059 | D43: Yes | E43: 2 | F43: kristopherstyle | G43: J.Crew | H43: J.Crew green mini dress in size m #grunge #retro #aesthetic | I43: M | J43: 16.15 | K43: 7.99 | L43: 40.6 | M43: 0 | N43: 0 | O43: 2.35 | P43: 2.96 | R43: STRIPE | S43: 46081 | T43: 46084 | U43: Dresses | V43: Krista Bell MD | W43: 35182 Javier Orchard | Y43: Jennyhaven | Z43: LA | AA43: 78723 | AB43: US | AC43: 1.26 | AF43: =IF(OR(A43="",C43=""),"",A43-C43) -> 20 | AG43: =IF(A43="","",IF(D43="No",IFERROR(K43*1,0),IF(D43="Yes",IFERROR(K43/E43,0),""))) -> 3.995 | AH43: =IF(A43="","",IFERROR(N43*1,0)+IFERROR(O43*1,0)+IFERROR(P43*1,0)+IFERROR(Q43*1,0)) -> 5.31 | AI43: {=IF(A43="","",IFERROR(INDEX(Listings!A:A,MATCH(TEXT(C43,"MM/DD/YYYY")&G43&U43,Listings!J$2:J$201,0)+1),""))} -> 61
A44: 46079 | B44: 05:38 PM | C44: 46061 | D44: Yes | F44: kristopherstyle | G44: Cotton Natural | H44: Cotton Natural burgundy leggings in size xl #aesthetic #grunge | I44: XL | J44: 13.5 | N44: 0 | R44: STRIPE | S44: 46081 | T44: 46084 | U44: Bottoms | V44: Krista Bell MD | W44: 35182 Javier Orchard | Y44: Jennyhaven | Z44: LA | AA44: 78723 | AB44: US | AF44: =IF(OR(A44="",C44=""),"",A44-C44) -> 18 | AG44: =IF(A44="","",IF(D44="No",IFERROR(K44*1,0),IF(D44="Yes",IFERROR(K44/E44,0),""))) -> 0 | AH44: =IF(A44="","",IFERROR(N44*1,0)+IFERROR(O44*1,0)+IFERROR(P44*1,0)+IFERROR(Q44*1,0)) -> 0 | AI44: {=IF(A44="","",IFERROR(INDEX(Listings!A:A,MATCH(TEXT(C44,"MM/DD/YYYY")&G44&U44,Listings!J$2:J$201,0)+1),""))} -> 63
A45: 46079 | B45: 11:26 PM | C45: 46070 | D45: No | F45: robert_carlson | G45: H&M | H45: H&M cream mini dress in size l #aesthetic #vintage #boho #preppy | I45: L | J45: 39 | K45: 3.99 | L45: 46.89 | M45: 0 | N45: 0 | O45: 3.08 | P45: 3.9 | R45: STRIPE | S45: 46081 | T45: 46084 | U45: Dresses | V45: David Grant | W45: 677 Dalton Meadow | Y45: Ashleyton | Z45: MO | AA45: 80406 | AB45: US | AF45: =IF(OR(A45="",C45=""),"",A45-C45) -> 9 | AG45: =IF(A45="","",IF(D45="No",IFERROR(K45*1,0),IF(D45="Yes",IFERROR(K45/E45,0),""))) -> 3.99 | AH45: =IF(A45="","",IFERROR(N45*1,0)+IFERROR(O45*1,0)+IFERROR(P45*1,0)+IFERROR(Q45*1,0)) -> 6.98 | AI45: {=IF(A45="","",IFERROR(INDEX(Listings!A:A,MATCH(TEXT(C45,"MM/DD/YYYY")&G45&U45,Listings!J$2:J$201,0)+1),""))} -> 65
A46: 46083 | B46: 07:25 AM | C46: 46080 | D46: No | F46: richardwear | G46: Self Esteem | H46: Self Esteem olive oversized dress in size xl #boho #grunge #casual | I46: XL | J46: 33 | K46: 7.99 | L46: 44.29 | M46: 0 | N46: 0 | O46: 2.61 | P46: 3.3 | R46: STRIPE | S46: 46085 | T46: 46088 | U46: Dresses | V46: John Torres | W46: 877 Carly Meadows Suite 940 | Y46: East Suzanneshire | Z46: KY | AA46: 77456 | AB46: US | AC46: 2.19 | AF46: =IF(OR(A46="",C46=""),"",A46-C46) -> 3 | AG46: =IF(A46="","",IF(D46="No",IFERROR(K46*1,0),IF(D46="Yes",IFERROR(K46/E46,0),""))) -> 7.99 | AH46: =IF(A46="","",IFERROR(N46*1,0)+IFERROR(O46*1,0)+IFERROR(P46*1,0)+IFERROR(Q46*1,0)) -> 5.91 | AI46: {=IF(A46="","",IFERROR(INDEX(Listings!A:A,MATCH(TEXT(C46,"MM/DD/YYYY")&G46&U46,Listings!J$2:J$201,0)+1),""))} -> 71
A47: 46084 | B47: 09:46 AM | C47: 46077 | D47: No | F47: colleencloset | G47: Adidas | H47: Adidas red button-down shirt in size xs #boho #preppy #minimalist | I47: XS | J47: 15.75 | K47: 4.99 | L47: 22.32 | M47: 0 | N47: 0 | O47: 1.24 | P47: 1.58 | R47: STRIPE | S47: 46086 | T47: 46090 | U47: Tops | V47: Annette Farmer | W47: 123 Andrea Estate Apt. 679 | Y47: Carterbury | Z47: IN | AA47: 38263 | AB47: US | AF47: =IF(OR(A47="",C47=""),"",A47-C47) -> 7 | AG47: =IF(A47="","",IF(D47="No",IFERROR(K47*1,0),IF(D47="Yes",IFERROR(K47/E47,0),""))) -> 4.99 | AH47: =IF(A47="","",IFERROR(N47*1,0)+IFERROR(O47*1,0)+IFERROR(P47*1,0)+IFERROR(Q47*1,0)) -> 2.82 | AI47: {=IF(A47="","",IFERROR(INDEX(Listings!A:A,MATCH(TEXT(C47,"MM/DD/YYYY")&G47&U47,Listings!J$2:J$201,0)+1),""))} -> 67
A48: 46087 | B48: 09:10 AM | C48: 46077 | D48: No | F48: gracebra | G48: Banana Republic | H48: Banana Republic black sundress in size m #casual #preppy #sustainable #streetwear #y2k | I48: M | J48: 29 | K48: 6.49 | L48: 38.39 | M48: 0 | N48: 0 | O48: 2.29 | P48: 2.9 | R48: STRIPE | S48: 46089 | T48: 46092 | U48: Dresses | V48: Michele Gibson | W48: 1832 Serrano Cliffs | Y48: East Laurashire | Z48: TN | AA48: 38329 | AB48: US | AC48: 1.79 | AF48: =IF(OR(A48="",C48=""),"",A48-C48) -> 10 | AG48: =IF(A48="","",IF(D48="No",IFERROR(K48*1,0),IF(D48="Yes",IFERROR(K48/E48,0),""))) -> 6.49 | AH48: =IF(A48="","",IFERROR(N48*1,0)+IFERROR(O48*1,0)+IFERROR(P48*1,0)+IFERROR(Q48*1,0)) -> 5.19 | AI48: {=IF(A48="","",IFERROR(INDEX(Listings!A:A,MATCH(TEXT(C48,"MM/DD/YYYY")&G48&U48,Listings!J$2:J$201,0)+1),""))} -> 69
A49: 46096 | B49: 10:37 PM | C49: 46087 | D49: No | F49: shopmaureen | G49: Free People | H49: Free People green button-down shirt in size s #y2k #sustainable | I49: S | J49: 24 | K49: 7.99 | L49: 34.39 | M49: 0 | N49: 0 | O49: 1.9 | P49: 2.4 | R49: STRIPE | S49: 46098 | T49: 46102 | U49: Tops | V49: Jason Walker | W49: 1274 Perry Orchard | Y49: Sanchezside | Z49: AZ | AA49: 19459 | AB49: US | AC49: 2.1 | AF49: =IF(OR(A49="",C49=""),"",A49-C49) -> 9 | AG49: =IF(A49="","",IF(D49="No",IFERROR(K49*1,0),IF(D49="Yes",IFERROR(K49/E49,0),""))) -> 7.99 | AH49: =IF(A49="","",IFERROR(N49*1,0)+IFERROR(O49*1,0)+IFERROR(P49*1,0)+IFERROR(Q49*1,0)) -> 4.3 | AI49: {=IF(A49="","",IFERROR(INDEX(Listings!A:A,MATCH(TEXT(C49,"MM/DD/YYYY")&G49&U49,Listings!J$2:J$201,0)+1),""))} -> 76
A50: 46097 | B50: 11:47 PM | C50: 46092 | D50: No | F50: closetsarah | G50: Self Esteem | H50: Self Esteem cream knit shorts in size l #preppy #cottagecore #casual #retro #thrift | I50: L | J50: 13 | K50: 7.99 | L50: 22.29 | M50: 0 | N50: 0 | O50: 1.03 | P50: 1.3 | R50: STRIPE | S50: 46099 | T50: 46103 | U50: Bottoms | V50: Mr. Phillip Bennett | W50: 396 Melissa Loop | Y50: West Juliefurt | Z50: MD | AA50: 51105 | AB50: US | AF50: =IF(OR(A50="",C50=""),"",A50-C50) -> 5 | AG50: =IF(A50="","",IF(D50="No",IFERROR(K50*1,0),IF(D50="Yes",IFERROR(K50/E50,0),""))) -> 7.99 | AH50: =IF(A50="","",IFERROR(N50*1,0)+IFERROR(O50*1,0)+IFERROR(P50*1,0)+IFERROR(Q50*1,0)) -> 2.33 | AI50: {=IF(A50="","",IFERROR(INDEX(Listings!A:A,MATCH(TEXT(C50,"MM/DD/YYYY")&G50&U50,Listings!J$2:J$201,0)+1),""))} -> 79
A51: 46101 | B51: 07:23 PM | C51: 46082 | D51: No | F51: heather_roberts | G51: Tommy Hilfiger | H51: Tommy Hilfiger gray cropped ribbed top in size l #minimalist #streetwear | I51: L | J51: 23 | K51: 7.99 | L51: 33.29 | M51: 0 | N51: 0 | O51: 1.82 | P51: 2.3 | R51: STRIPE | S51: 46103 | T51: 46105 | U51: Tops | V51: Shannon Rivera | W51: 071 King Crescent Suite 808 | Y51: Gutierrezborough | Z51: MD | AA51: 68453 | AB51: US | AC51: 1.17 | AF51: =IF(OR(A51="",C51=""),"",A51-C51) -> 19 | AG51: =IF(A51="","",IF(D51="No",IFERROR(K51*1,0),IF(D51="Yes",IFERROR(K51/E51,0),""))) -> 7.99 | AH51: =IF(A51="","",IFERROR(N51*1,0)+IFERROR(O51*1,0)+IFERROR(P51*1,0)+IFERROR(Q51*1,0)) -> 4.12 | AI51: {=IF(A51="","",IFERROR(INDEX(Listings!A:A,MATCH(TEXT(C51,"MM/DD/YYYY")&G51&U51,Listings!J$2:J$201,0)+1),""))} -> 72
A52: 46102 | B52: 07:30 AM | C52: 46095 | D52: No | F52: styletammie | G52: Aerie | H52: Aerie teal mini dress in size s #streetwear #sustainable #retro #preppy | I52: S | J52: 21 | K52: 6.49 | L52: 29.59 | M52: 0 | N52: 0 | O52: 1.66 | P52: 2.1 | R52: STRIPE | S52: 46104 | T52: 46106 | U52: Dresses | V52: Rebecca Pearson MD | W52: 951 Garcia Motorway | Y52: Lake Douglasberg | Z52: FL | AA52: 10308 | AB52: US | AC52: 1.76 | AF52: =IF(OR(A52="",C52=""),"",A52-C52) -> 7 | AG52: =IF(A52="","",IF(D52="No",IFERROR(K52*1,0),IF(D52="Yes",IFERROR(K52/E52,0),""))) -> 6.49 | AH52: =IF(A52="","",IFERROR(N52*1,0)+IFERROR(O52*1,0)+IFERROR(P52*1,0)+IFERROR(Q52*1,0)) -> 3.76 | AI52: {=IF(A52="","",IFERROR(INDEX(Listings!A:A,MATCH(TEXT(C52,"MM/DD/YYYY")&G52&U52,Listings!J$2:J$201,0)+1),""))} -> 80
A53: 46103 | B53: 10:28 AM | C53: 46096 | D53: No | F53: heather12 | G53: Zara | H53: Zara teal henley in size s #cottagecore #y2k #preppy #thrift | I53: S | J53: 22.5 | K53: 6.49 | L53: 31.24 | M53: 0 | N53: 0 | O53: 1.78 | P53: 2.25 | R53: STRIPE | S53: 46105 | T53: 46108 | U53: Tops | V53: Wayne Morgan | W53: 8657 Christina Freeway | Y53: Wendyland | Z53: NY | AA53: 57382 | AB53: US | AC53: 1.99 | AF53: =IF(OR(A53="",C53=""),"",A53-C53) -> 7 | AG53: =IF(A53="","",IF(D53="No",IFERROR(K53*1,0),IF(D53="Yes",IFERROR(K53/E53,0),""))) -> 6.49 | AH53: =IF(A53="","",IFERROR(N53*1,0)+IFERROR(O53*1,0)+IFERROR(P53*1,0)+IFERROR(Q53*1,0)) -> 4.03 | AI53: {=IF(A53="","",IFERROR(INDEX(Listings!A:A,MATCH(TEXT(C53,"MM/DD/YYYY")&G53&U53,Listings!J$2:J$201,0)+1),""))} -> 83
A54: 46104 | B54: 01:28 PM | C54: 46096 | D54: No | F54: thriftgeorge | G54: Nike | H54: Nike navy y2k sweater in size xl #preppy #retro | I54: XL | J54: 11 | K54: 6.49 | L54: 18.59 | M54: 0 | N54: 0 | O54: 0.87 | P54: 1.1 | R54: STRIPE | S54: 46106 | T54: 46108 | U54: Tops | V54: Kylie Sparks | W54: 693 Durham Divide | Y54: South Dana | Z54: SC | AA54: 60737 | AB54: US | AF54: =IF(OR(A54="",C54=""),"",A54-C54) -> 8 | AG54: =IF(A54="","",IF(D54="No",IFERROR(K54*1,0),IF(D54="Yes",IFERROR(K54/E54,0),""))) -> 6.49 | AH54: =IF(A54="","",IFERROR(N54*1,0)+IFERROR(O54*1,0)+IFERROR(P54*1,0)+IFERROR(Q54*1,0)) -> 1.97 | AI54: {=IF(A54="","",IFERROR(INDEX(Listings!A:A,MATCH(TEXT(C54,"MM/DD/YYYY")&G54&U54,Listings!J$2:J$201,0)+1),""))} -> 81
A55: 46106 | B55: 01:30 PM | C55: 46080 | D55: No | F55: joseph_williams | G55: Express | H55: Express brown cargo pants in size s #grunge #aesthetic #boho | I55: S | J55: 11 | K55: 6.49 | L55: 18.59 | M55: 0 | N55: 0 | O55: 0.87 | P55: 1.1 | R55: STRIPE | S55: 46108 | T55: 46111 | U55: Bottoms | V55: Yvonne Chambers | W55: 8742 Walters Overpass | Y55: South Michaelmouth | Z55: MI | AA55: 42582 | AB55: US | AC55: 0.86 | AF55: =IF(OR(A55="",C55=""),"",A55-C55) -> 26 | AG55: =IF(A55="","",IF(D55="No",IFERROR(K55*1,0),IF(D55="Yes",IFERROR(K55/E55,0),""))) -> 6.49 | AH55: =IF(A55="","",IFERROR(N55*1,0)+IFERROR(O55*1,0)+IFERROR(P55*1,0)+IFERROR(Q55*1,0)) -> 1.97 | AI55: {=IF(A55="","",IFERROR(INDEX(Listings!A:A,MATCH(TEXT(C55,"MM/DD/YYYY")&G55&U55,Listings!J$2:J$201,0)+1),""))} -> 70
A56: 46106 | B56: 06:10 PM | C56: 46092 | D56: No | F56: closetnatasha | G56: Aerie | H56: Aerie tie-dye overall shorts in size l #vintage #y2k | I56: L | J56: 20 | K56: 3.99 | L56: 25.99 | M56: 0 | N56: 0 | O56: 1.58 | P56: 2 | R56: STRIPE | S56: 46108 | T56: 46112 | U56: Jumpsuits/Rompers | V56: Thomas Romero | W56: 6584 Justin Hills | Y56: Grimesmouth | Z56: CO | AA56: 71093 | AB56: US | AC56: 1.28 | AF56: =IF(OR(A56="",C56=""),"",A56-C56) -> 14 | AG56: =IF(A56="","",IF(D56="No",IFERROR(K56*1,0),IF(D56="Yes",IFERROR(K56/E56,0),""))) -> 3.99 | AH56: =IF(A56="","",IFERROR(N56*1,0)+IFERROR(O56*1,0)+IFERROR(P56*1,0)+IFERROR(Q56*1,0)) -> 3.58 | AI56: {=IF(A56="","",IFERROR(INDEX(Listings!A:A,MATCH(TEXT(C56,"MM/DD/YYYY")&G56&U56,Listings!J$2:J$201,0)+1),""))} -> 78
A57: 46106 | B57: 05:12 PM | C57: 46102 | D57: No | F57: shoprachel | G57: Victoria's Secret | H57: Victoria's Secret floral cotton skirt in size m #casual #aesthetic #preppy #y2k #grunge | I57: M | J57: 17 | K57: 5.99 | L57: 24.69 | M57: 0 | N57: 0 | O57: 1.34 | P57: 1.7 | R57: STRIPE | S57: 46108 | T57: 46112 | U57: Bottoms | V57: Adam Ballard | W57: 75946 Bryant Hollow | Y57: South Melissa | Z57: OK | AA57: 14480 | AB57: US | AC57: 1.67 | AF57: =IF(OR(A57="",C57=""),"",A57-C57) -> 4 | AG57: =IF(A57="","",IF(D57="No",IFERROR(K57*1,0),IF(D57="Yes",IFERROR(K57/E57,0),""))) -> 5.99 | AH57: =IF(A57="","",IFERROR(N57*1,0)+IFERROR(O57*1,0)+IFERROR(P57*1,0)+IFERROR(Q57*1,0)) -> 3.04 | AI57: {=IF(A57="","",IFERROR(INDEX(Listings!A:A,MATCH(TEXT(C57,"MM/DD/YYYY")&G57&U57,Listings!J$2:J$201,0)+1),""))} -> 85
A58: 46110 | B58: 09:39 PM | C58: 46103 | D58: No | F58: victoria_phillips | G58: Ralph Lauren | H58: Ralph Lauren teal vintage romper in size xs #cottagecore #thrift | I58: XS | J58: 11 | K58: 11.99 | L58: 24.09 | M58: 0 | N58: 0 | O58: 0.87 | P58: 1.1 | R58: STRIPE | S58: 46112 | T58: 46116 | U58: Jumpsuits/Rompers | V58: Kenneth Andrews | W58: 0909 Wall Heights Apt. 953 | Y58: New John | Z58: KY | AA58: 99536 | AB58: US | AF58: =IF(OR(A58="",C58=""),"",A58-C58) -> 7 | AG58: =IF(A58="","",IF(D58="No",IFERROR(K58*1,0),IF(D58="Yes",IFERROR(K58/E58,0),""))) -> 11.99 | AH58: =IF(A58="","",IFERROR(N58*1,0)+IFERROR(O58*1,0)+IFERROR(P58*1,0)+IFERROR(Q58*1,0)) -> 1.97 | AI58: {=IF(A58="","",IFERROR(INDEX(Listings!A:A,MATCH(TEXT(C58,"MM/DD/YYYY")&G58&U58,Listings!J$2:J$201,0)+1),""))} -> 86
A59: 46111 | B59: 01:28 PM | C59: 46085 | D59: Yes | E59: 2 | F59: kathleencloset | G59: Deb | H59: Deb striped graphic tee in size l #sustainable #boho #cottagecore #thrift | I59: L | J59: 15.3 | K59: 11.99 | L59: 42.9 | M59: 0 | N59: 0 | O59: 2.22 | P59: 2.81 | R59: STRIPE | S59: 46113 | T59: 46115 | U59: Tops | V59: Peter Garrett | W59: 8247 Martinez Roads | Y59: Lake Eric | Z59: OR | AA59: 72700 | AB59: US | AC59: 1.34 | AF59: =IF(OR(A59="",C59=""),"",A59-C59) -> 26 | AG59: =IF(A59="","",IF(D59="No",IFERROR(K59*1,0),IF(D59="Yes",IFERROR(K59/E59,0),""))) -> 5.995 | AH59: =IF(A59="","",IFERROR(N59*1,0)+IFERROR(O59*1,0)+IFERROR(P59*1,0)+IFERROR(Q59*1,0)) -> 5.03 | AI59: {=IF(A59="","",IFERROR(INDEX(Listings!A:A,MATCH(TEXT(C59,"MM/DD/YYYY")&G59&U59,Listings!J$2:J$201,0)+1),""))} -> 73
A60: 46111 | B60: 01:28 PM | C60: 46087 | D60: Yes | F60: kathleencloset | G60: Ralph Lauren | H60: Ralph Lauren striped graphic tee in size xs #retro #boho #vintage | I60: XS | J60: 12.8 | N60: 0 | R60: STRIPE | S60: 46113 | T60: 46115 | U60: Tops | V60: Peter Garrett | W60: 8247 Martinez Roads | Y60: Lake Eric | Z60: OR | AA60: 72700 | AB60: US | AF60: =IF(OR(A60="",C60=""),"",A60-C60) -> 24 | AG60: =IF(A60="","",IF(D60="No",IFERROR(K60*1,0),IF(D60="Yes",IFERROR(K60/E60,0),""))) -> 0 | AH60: =IF(A60="","",IFERROR(N60*1,0)+IFERROR(O60*1,0)+IFERROR(P60*1,0)+IFERROR(Q60*1,0)) -> 0 | AI60: {=IF(A60="","",IFERROR(INDEX(Listings!A:A,MATCH(TEXT(C60,"MM/DD/YYYY")&G60&U60,Listings!J$2:J$201,0)+1),""))} -> 75
A61: 46121 | B61: 02:33 PM | C61: 46096 | D61: No | F61: craigcloset | G61: Express | H61: Express floral fitted sneakers in size 7 #cottagecore #preppy #aesthetic | I61: 7 | J61: 12 | K61: 4.99 | L61: 18.19 | M61: 0 | N61: 0 | O61: 0.95 | P61: 1.2 | R61: STRIPE | S61: 46123 | T61: 46126 | U61: Footwear | V61: Paige Padilla | W61: 400 Flynn Hill | Y61: Nicholasberg | Z61: MO | AA61: 32508 | AB61: US | AC61: 0.81 | AF61: =IF(OR(A61="",C61=""),"",A61-C61) -> 25 | AG61: =IF(A61="","",IF(D61="No",IFERROR(K61*1,0),IF(D61="Yes",IFERROR(K61/E61,0),""))) -> 4.99 | AH61: =IF(A61="","",IFERROR(N61*1,0)+IFERROR(O61*1,0)+IFERROR(P61*1,0)+IFERROR(Q61*1,0)) -> 2.15 | AI61: {=IF(A61="","",IFERROR(INDEX(Listings!A:A,MATCH(TEXT(C61,"MM/DD/YYYY")&G61&U61,Listings!J$2:J$201,0)+1),""))} -> 82
AF62: =IF(OR(A62="",C62=""),"",A62-C62) | AG62: =IF(A62="","",IF(D62="No",IFERROR(K62*1,0),IF(D62="Yes",IFERROR(K62/E62,0),""))) | AH62: =IF(A62="","",IFERROR(N62*1,0)+IFERROR(O62*1,0)+IFERROR(P62*1,0)+IFERROR(Q62*1,0)) | AI62: {=IF(A62="","",IFERROR(INDEX(Listings!A:A,MATCH(TEXT(C62,"MM/DD/YYYY")&G62&U62,Listings!J$2:J$201,0)+1),""))}
AF63: =IF(OR(A63="",C63=""),"",A63-C63) | AG63: =IF(A63="","",IF(D63="No",IFERROR(K63*1,0),IF(D63="Yes",IFERROR(K63/E63,0),""))) | AH63: =IF(A63="","",IFERROR(N63*1,0)+IFERROR(O63*1,0)+IFERROR(P63*1,0)+IFERROR(Q63*1,0)) | AI63: {=IF(A63="","",IFERROR(INDEX(Listings!A:A,MATCH(TEXT(C63,"MM/DD/YYYY")&G63&U63,Listings!J$2:J$201,0)+1),""))}
AF64: =IF(OR(A64="",C64=""),"",A64-C64) | AG64: =IF(A64="","",IF(D64="No",IFERROR(K64*1,0),IF(D64="Yes",IFERROR(K64/E64,0),""))) | AH64: =IF(A64="","",IFERROR(N64*1,0)+IFERROR(O64*1,0)+IFERROR(P64*1,0)+IFERROR(Q64*1,0)) | AI64: {=IF(A64="","",IFERROR(INDEX(Listings!A:A,MATCH(TEXT(C64,"MM/DD/YYYY")&G64&U64,Listings!J$2:J$201,0)+1),""))}
AF65: =IF(OR(A65="",C65=""),"",A65-C65) | AG65: =IF(A65="","",IF(D65="No",IFERROR(K65*1,0),IF(D65="Yes",IFERROR(K65/E65,0),""))) | AH65: =IF(A65="","",IFERROR(N65*1,0)+IFERROR(O65*1,0)+IFERROR(P65*1,0)+IFERROR(Q65*1,0)) | AI65: {=IF(A65="","",IFERROR(INDEX(Listings!A:A,MATCH(TEXT(C65,"MM/DD/YYYY")&G65&U65,Listings!J$2:J$201,0)+1),""))}
AF66: =IF(OR(A66="",C66=""),"",A66-C66) | AG66: =IF(A66="","",IF(D66="No",IFERROR(K66*1,0),IF(D66="Yes",IFERROR(K66/E66,0),""))) | AH66: =IF(A66="","",IFERROR(N66*1,0)+IFERROR(O66*1,0)+IFERROR(P66*1,0)+IFERROR(Q66*1,0)) | AI66: {=IF(A66="","",IFERROR(INDEX(Listings!A:A,MATCH(TEXT(C66,"MM/DD/YYYY")&G66&U66,Listings!J$2:J$201,0)+1),""))}
AF67: =IF(OR(A67="",C67=""),"",A67-C67) | AG67: =IF(A67="","",IF(D67="No",IFERROR(K67*1,0),IF(D67="Yes",IFERROR(K67/E67,0),""))) | AH67: =IF(A67="","",IFERROR(N67*1,0)+IFERROR(O67*1,0)+IFERROR(P67*1,0)+IFERROR(Q67*1,0)) | AI67: {=IF(A67="","",IFERROR(INDEX(Listings!A:A,MATCH(TEXT(C67,"MM/DD/YYYY")&G67&U67,Listings!J$2:J$201,0)+1),""))}
AF68: =IF(OR(A68="",C68=""),"",A68-C68) | AG68: =IF(A68="","",IF(D68="No",IFERROR(K68*1,0),IF(D68="Yes",IFERROR(K68/E68,0),""))) | AH68: =IF(A68="","",IFERROR(N68*1,0)+IFERROR(O68*1,0)+IFERROR(P68*1,0)+IFERROR(Q68*1,0)) | AI68: {=IF(A68="","",IFERROR(INDEX(Listings!A:A,MATCH(TEXT(C68,"MM/DD/YYYY")&G68&U68,Listings!J$2:J$201,0)+1),""))}
AF69: =IF(OR(A69="",C69=""),"",A69-C69) | AG69: =IF(A69="","",IF(D69="No",IFERROR(K69*1,0),IF(D69="Yes",IFERROR(K69/E69,0),""))) | AH69: =IF(A69="","",IFERROR(N69*1,0)+IFERROR(O69*1,0)+IFERROR(P69*1,0)+IFERROR(Q69*1,0)) | AI69: {=IF(A69="","",IFERROR(INDEX(Listings!A:A,MATCH(TEXT(C69,"MM/DD/YYYY")&G69&U69,Listings!J$2:J$201,0)+1),""))}
AF70: =IF(OR(A70="",C70=""),"",A70-C70) | AG70: =IF(A70="","",IF(D70="No",IFERROR(K70*1,0),IF(D70="Yes",IFERROR(K70/E70,0),""))) | AH70: =IF(A70="","",IFERROR(N70*1,0)+IFERROR(O70*1,0)+IFERROR(P70*1,0)+IFERROR(Q70*1,0)) | AI70: {=IF(A70="","",IFERROR(INDEX(Listings!A:A,MATCH(TEXT(C70,"MM/DD/YYYY")&G70&U70,Listings!J$2:J$201,0)+1),""))}
AF71: =IF(OR(A71="",C71=""),"",A71-C71) | AG71: =IF(A71="","",IF(D71="No",IFERROR(K71*1,0),IF(D71="Yes",IFERROR(K71/E71,0),""))) | AH71: =IF(A71="","",IFERROR(N71*1,0)+IFERROR(O71*1,0)+IFERROR(P71*1,0)+IFERROR(Q71*1,0)) | AI71: {=IF(A71="","",IFERROR(INDEX(Listings!A:A,MATCH(TEXT(C71,"MM/DD/YYYY")&G71&U71,Listings!J$2:J$201,0)+1),""))}
AF72: =IF(OR(A72="",C72=""),"",A72-C72) | AG72: =IF(A72="","",IF(D72="No",IFERROR(K72*1,0),IF(D72="Yes",IFERROR(K72/E72,0),""))) | AH72: =IF(A72="","",IFERROR(N72*1,0)+IFERROR(O72*1,0)+IFERROR(P72*1,0)+IFERROR(Q72*1,0)) | AI72: {=IF(A72="","",IFERROR(INDEX(Listings!A:A,MATCH(TEXT(C72,"MM/DD/YYYY")&G72&U72,Listings!J$2:J$201,0)+1),""))}
AF73: =IF(OR(A73="",C73=""),"",A73-C73) | AG73: =IF(A73="","",IF(D73="No",IFERROR(K73*1,0),IF(D73="Yes",IFERROR(K73/E73,0),""))) | AH73: =IF(A73="","",IFERROR(N73*1,0)+IFERROR(O73*1,0)+IFERROR(P73*1,0)+IFERROR(Q73*1,0)) | AI73: {=IF(A73="","",IFERROR(INDEX(Listings!A:A,MATCH(TEXT(C73,"MM/DD/YYYY")&G73&U73,Listings!J$2:J$201,0)+1),""))}
... AF189: =IF(OR(A189="",C189=""),"",A189-C189) | AG189: =IF(A189="","",IF(D189="No",IFERROR(K189*1,0),IF(D189="Yes",IFERROR(K189/E189,0),""))) | AH189: =IF(A189="","",IFERROR(N189*1,0)+IFERROR(O189*1,0)+IFERROR(P189*1,0)+IFERROR(Q189*1,0)) | AI189: {=IF(A189="","",IFERROR(INDEX(Listings!A:A,MATCH(TEXT(C189,"MM/DD/YYYY")&G189&U189,Listings!J$2:J$201,0)+1),""))}
AC190: =IF(OR(A190="",C190=""),"",DATEVALUE(A190)-DATEVALUE(C190)) | AD190: =IF(A190="","",IF(D190="No",IFERROR(VALUE(SUBSTITUTE(K190,"$",""))*1,0),IF(D190="Yes",IFERROR(VALUE(SUBSTITUTE(K190,"$",""))/VALUE(E190),0),""))) | AE190: =IF(A190="","",IFERROR(VALUE(SUBSTITUTE(N190,"$",""))*1,0)+IFERROR(VALUE(SUBSTITUTE(O190,"$",""))*1,0)+IFERROR(VALUE(SUBSTITUTE(P190,"$",""))*1,0)+IFERROR(VALUE(SUBSTITUTE(Q190,"$",""))*1,0)) | AF190: =IF(OR(A190="",C190=""),"",A190-C190) | AG190: =IF(A190="","",IF(D190="No",IFERROR(K190*1,0),IF(D190="Yes",IFERROR(K190/E190,0),""))) | AH190: =IF(A190="","",IFERROR(N190*1,0)+IFERROR(O190*1,0)+IFERROR(P190*1,0)+IFERROR(Q190*1,0)) | AI190: {=IF(A190="","",IFERROR(INDEX(Listings!A:A,MATCH(TEXT(C190,"MM/DD/YYYY")&G190&U190,Listings!J$2:J$201,0)+1),""))}
AC191: =IF(OR(A191="",C191=""),"",DATEVALUE(A191)-DATEVALUE(C191)) | AD191: =IF(A191="","",IF(D191="No",IFERROR(VALUE(SUBSTITUTE(K191,"$",""))*1,0),IF(D191="Yes",IFERROR(VALUE(SUBSTITUTE(K191,"$",""))/VALUE(E191),0),""))) | AE191: =IF(A191="","",IFERROR(VALUE(SUBSTITUTE(N191,"$",""))*1,0)+IFERROR(VALUE(SUBSTITUTE(O191,"$",""))*1,0)+IFERROR(VALUE(SUBSTITUTE(P191,"$",""))*1,0)+IFERROR(VALUE(SUBSTITUTE(Q191,"$",""))*1,0)) | AF191: =IF(OR(A191="",C191=""),"",A191-C191) | AG191: =IF(A191="","",IF(D191="No",IFERROR(K191*1,0),IF(D191="Yes",IFERROR(K191/E191,0),""))) | AH191: =IF(A191="","",IFERROR(N191*1,0)+IFERROR(O191*1,0)+IFERROR(P191*1,0)+IFERROR(Q191*1,0)) | AI191: {=IF(A191="","",IFERROR(INDEX(Listings!A:A,MATCH(TEXT(C191,"MM/DD/YYYY")&G191&U191,Listings!J$2:J$201,0)+1),""))}
AC192: =IF(OR(A192="",C192=""),"",DATEVALUE(A192)-DATEVALUE(C192)) | AD192: =IF(A192="","",IF(D192="No",IFERROR(VALUE(SUBSTITUTE(K192,"$",""))*1,0),IF(D192="Yes",IFERROR(VALUE(SUBSTITUTE(K192,"$",""))/VALUE(E192),0),""))) | AE192: =IF(A192="","",IFERROR(VALUE(SUBSTITUTE(N192,"$",""))*1,0)+IFERROR(VALUE(SUBSTITUTE(O192,"$",""))*1,0)+IFERROR(VALUE(SUBSTITUTE(P192,"$",""))*1,0)+IFERROR(VALUE(SUBSTITUTE(Q192,"$",""))*1,0)) | AF192: =IF(OR(A192="",C192=""),"",A192-C192) | AG192: =IF(A192="","",IF(D192="No",IFERROR(K192*1,0),IF(D192="Yes",IFERROR(K192/E192,0),""))) | AH192: =IF(A192="","",IFERROR(N192*1,0)+IFERROR(O192*1,0)+IFERROR(P192*1,0)+IFERROR(Q192*1,0)) | AI192: {=IF(A192="","",IFERROR(INDEX(Listings!A:A,MATCH(TEXT(C192,"MM/DD/YYYY")&G192&U192,Listings!J$2:J$201,0)+1),""))}
AC193: =IF(OR(A193="",C193=""),"",DATEVALUE(A193)-DATEVALUE(C193)) | AD193: =IF(A193="","",IF(D193="No",IFERROR(VALUE(SUBSTITUTE(K193,"$",""))*1,0),IF(D193="Yes",IFERROR(VALUE(SUBSTITUTE(K193,"$",""))/VALUE(E193),0),""))) | AE193: =IF(A193="","",IFERROR(VALUE(SUBSTITUTE(N193,"$",""))*1,0)+IFERROR(VALUE(SUBSTITUTE(O193,"$",""))*1,0)+IFERROR(VALUE(SUBSTITUTE(P193,"$",""))*1,0)+IFERROR(VALUE(SUBSTITUTE(Q193,"$",""))*1,0)) | AF193: =IF(OR(A193="",C193=""),"",A193-C193) | AG193: =IF(A193="","",IF(D193="No",IFERROR(K193*1,0),IF(D193="Yes",IFERROR(K193/E193,0),""))) | AH193: =IF(A193="","",IFERROR(N193*1,0)+IFERROR(O193*1,0)+IFERROR(P193*1,0)+IFERROR(Q193*1,0)) | AI193: {=IF(A193="","",IFERROR(INDEX(Listings!A:A,MATCH(TEXT(C193,"MM/DD/YYYY")&G193&U193,Listings!J$2:J$201,0)+1),""))}
AC194: =IF(OR(A194="",C194=""),"",DATEVALUE(A194)-DATEVALUE(C194)) | AD194: =IF(A194="","",IF(D194="No",IFERROR(VALUE(SUBSTITUTE(K194,"$",""))*1,0),IF(D194="Yes",IFERROR(VALUE(SUBSTITUTE(K194,"$",""))/VALUE(E194),0),""))) | AE194: =IF(A194="","",IFERROR(VALUE(SUBSTITUTE(N194,"$",""))*1,0)+IFERROR(VALUE(SUBSTITUTE(O194,"$",""))*1,0)+IFERROR(VALUE(SUBSTITUTE(P194,"$",""))*1,0)+IFERROR(VALUE(SUBSTITUTE(Q194,"$",""))*1,0)) | AF194: =IF(OR(A194="",C194=""),"",A194-C194) | AG194: =IF(A194="","",IF(D194="No",IFERROR(K194*1,0),IF(D194="Yes",IFERROR(K194/E194,0),""))) | AH194: =IF(A194="","",IFERROR(N194*1,0)+IFERROR(O194*1,0)+IFERROR(P194*1,0)+IFERROR(Q194*1,0)) | AI194: {=IF(A194="","",IFERROR(INDEX(Listings!A:A,MATCH(TEXT(C194,"MM/DD/YYYY")&G194&U194,Listings!J$2:J$201,0)+1),""))}
AC195: =IF(OR(A195="",C195=""),"",DATEVALUE(A195)-DATEVALUE(C195)) | AD195: =IF(A195="","",IF(D195="No",IFERROR(VALUE(SUBSTITUTE(K195,"$",""))*1,0),IF(D195="Yes",IFERROR(VALUE(SUBSTITUTE(K195,"$",""))/VALUE(E195),0),""))) | AE195: =IF(A195="","",IFERROR(VALUE(SUBSTITUTE(N195,"$",""))*1,0)+IFERROR(VALUE(SUBSTITUTE(O195,"$",""))*1,0)+IFERROR(VALUE(SUBSTITUTE(P195,"$",""))*1,0)+IFERROR(VALUE(SUBSTITUTE(Q195,"$",""))*1,0)) | AF195: =IF(OR(A195="",C195=""),"",A195-C195) | AG195: =IF(A195="","",IF(D195="No",IFERROR(K195*1,0),IF(D195="Yes",IFERROR(K195/E195,0),""))) | AH195: =IF(A195="","",IFERROR(N195*1,0)+IFERROR(O195*1,0)+IFERROR(P195*1,0)+IFERROR(Q195*1,0)) | AI195: {=IF(A195="","",IFERROR(INDEX(Listings!A:A,MATCH(TEXT(C195,"MM/DD/YYYY")&G195&U195,Listings!J$2:J$201,0)+1),""))}
AC196: =IF(OR(A196="",C196=""),"",DATEVALUE(A196)-DATEVALUE(C196)) | AD196: =IF(A196="","",IF(D196="No",IFERROR(VALUE(SUBSTITUTE(K196,"$",""))*1,0),IF(D196="Yes",IFERROR(VALUE(SUBSTITUTE(K196,"$",""))/VALUE(E196),0),""))) | AE196: =IF(A196="","",IFERROR(VALUE(SUBSTITUTE(N196,"$",""))*1,0)+IFERROR(VALUE(SUBSTITUTE(O196,"$",""))*1,0)+IFERROR(VALUE(SUBSTITUTE(P196,"$",""))*1,0)+IFERROR(VALUE(SUBSTITUTE(Q196,"$",""))*1,0)) | AF196: =IF(OR(A196="",C196=""),"",A196-C196) | AG196: =IF(A196="","",IF(D196="No",IFERROR(K196*1,0),IF(D196="Yes",IFERROR(K196/E196,0),""))) | AH196: =IF(A196="","",IFERROR(N196*1,0)+IFERROR(O196*1,0)+IFERROR(P196*1,0)+IFERROR(Q196*1,0)) | AI196: {=IF(A196="","",IFERROR(INDEX(Listings!A:A,MATCH(TEXT(C196,"MM/DD/YYYY")&G196&U196,Listings!J$2:J$201,0)+1),""))}
AC197: =IF(OR(A197="",C197=""),"",DATEVALUE(A197)-DATEVALUE(C197)) | AD197: =IF(A197="","",IF(D197="No",IFERROR(VALUE(SUBSTITUTE(K197,"$",""))*1,0),IF(D197="Yes",IFERROR(VALUE(SUBSTITUTE(K197,"$",""))/VALUE(E197),0),""))) | AE197: =IF(A197="","",IFERROR(VALUE(SUBSTITUTE(N197,"$",""))*1,0)+IFERROR(VALUE(SUBSTITUTE(O197,"$",""))*1,0)+IFERROR(VALUE(SUBSTITUTE(P197,"$",""))*1,0)+IFERROR(VALUE(SUBSTITUTE(Q197,"$",""))*1,0)) | AF197: =IF(OR(A197="",C197=""),"",A197-C197) | AG197: =IF(A197="","",IF(D197="No",IFERROR(K197*1,0),IF(D197="Yes",IFERROR(K197/E197,0),""))) | AH197: =IF(A197="","",IFERROR(N197*1,0)+IFERROR(O197*1,0)+IFERROR(P197*1,0)+IFERROR(Q197*1,0)) | AI197: {=IF(A197="","",IFERROR(INDEX(Listings!A:A,MATCH(TEXT(C197,"MM/DD/YYYY")&G197&U197,Listings!J$2:J$201,0)+1),""))}
AC198: =IF(OR(A198="",C198=""),"",DATEVALUE(A198)-DATEVALUE(C198)) | AD198: =IF(A198="","",IF(D198="No",IFERROR(VALUE(SUBSTITUTE(K198,"$",""))*1,0),IF(D198="Yes",IFERROR(VALUE(SUBSTITUTE(K198,"$",""))/VALUE(E198),0),""))) | AE198: =IF(A198="","",IFERROR(VALUE(SUBSTITUTE(N198,"$",""))*1,0)+IFERROR(VALUE(SUBSTITUTE(O198,"$",""))*1,0)+IFERROR(VALUE(SUBSTITUTE(P198,"$",""))*1,0)+IFERROR(VALUE(SUBSTITUTE(Q198,"$",""))*1,0)) | AF198: =IF(OR(A198="",C198=""),"",A198-C198) | AG198: =IF(A198="","",IF(D198="No",IFERROR(K198*1,0),IF(D198="Yes",IFERROR(K198/E198,0),""))) | AH198: =IF(A198="","",IFERROR(N198*1,0)+IFERROR(O198*1,0)+IFERROR(P198*1,0)+IFERROR(Q198*1,0)) | AI198: {=IF(A198="","",IFERROR(INDEX(Listings!A:A,MATCH(TEXT(C198,"MM/DD/YYYY")&G198&U198,Listings!J$2:J$201,0)+1),""))}
AC199: =IF(OR(A199="",C199=""),"",DATEVALUE(A199)-DATEVALUE(C199)) | AD199: =IF(A199="","",IF(D199="No",IFERROR(VALUE(SUBSTITUTE(K199,"$",""))*1,0),IF(D199="Yes",IFERROR(VALUE(SUBSTITUTE(K199,"$",""))/VALUE(E199),0),""))) | AE199: =IF(A199="","",IFERROR(VALUE(SUBSTITUTE(N199,"$",""))*1,0)+IFERROR(VALUE(SUBSTITUTE(O199,"$",""))*1,0)+IFERROR(VALUE(SUBSTITUTE(P199,"$",""))*1,0)+IFERROR(VALUE(SUBSTITUTE(Q199,"$",""))*1,0)) | AF199: =IF(OR(A199="",C199=""),"",A199-C199) | AG199: =IF(A199="","",IF(D199="No",IFERROR(K199*1,0),IF(D199="Yes",IFERROR(K199/E199,0),""))) | AH199: =IF(A199="","",IFERROR(N199*1,0)+IFERROR(O199*1,0)+IFERROR(P199*1,0)+IFERROR(Q199*1,0)) | AI199: {=IF(A199="","",IFERROR(INDEX(Listings!A:A,MATCH(TEXT(C199,"MM/DD/YYYY")&G199&U199,Listings!J$2:J$201,0)+1),""))}
AC200: =IF(OR(A200="",C200=""),"",DATEVALUE(A200)-DATEVALUE(C200)) | AD200: =IF(A200="","",IF(D200="No",IFERROR(VALUE(SUBSTITUTE(K200,"$",""))*1,0),IF(D200="Yes",IFERROR(VALUE(SUBSTITUTE(K200,"$",""))/VALUE(E200),0),""))) | AE200: =IF(A200="","",IFERROR(VALUE(SUBSTITUTE(N200,"$",""))*1,0)+IFERROR(VALUE(SUBSTITUTE(O200,"$",""))*1,0)+IFERROR(VALUE(SUBSTITUTE(P200,"$",""))*1,0)+IFERROR(VALUE(SUBSTITUTE(Q200,"$",""))*1,0)) | AF200: =IF(OR(A200="",C200=""),"",A200-C200) | AG200: =IF(A200="","",IF(D200="No",IFERROR(K200*1,0),IF(D200="Yes",IFERROR(K200/E200,0),""))) | AH200: =IF(A200="","",IFERROR(N200*1,0)+IFERROR(O200*1,0)+IFERROR(P200*1,0)+IFERROR(Q200*1,0)) | AI200: {=IF(A200="","",IFERROR(INDEX(Listings!A:A,MATCH(TEXT(C200,"MM/DD/YYYY")&G200&U200,Listings!J$2:J$201,0)+1),""))}

Sheet DepopSalesImport
A1: Date of sale | B1: Time of sale | C1: Date of listing | D1: Bundle | E1: Bundle - amount of items | F1: Buyer | G1: Brand | H1: Description | I1: Size | J1: Item price | K1: Buyer shipping cost | L1: Total | M1: USPS Cost | N1: Depop fee | O1: Depop Payments fee | P1: Buyer Marketplace Fee | Q1: Boosting fee | R1: Payment type | S1: Estimated payout date | T1: Payout arrival date | U1: Category | V1: Name | W1: Address Line 1 | X1: Address Line 2 | Y1: City | Z1: State | AA1: Post Code | AB1: Country | AC1: US Sales tax | AD1: Refunded to buyer amount | AE1: Fees refunded to seller
A2: 46123 | B2: 10:51 PM | C2: 46117 | D2: No | F2: adam54 | G2: Express | H2: Express navy y2k bottom in size m #y2k #navy #thrift #depop | I2: M | J2: 17.3 | K2: 4.99 | L2: 24.02 | M2: 0 | N2: 0 | O2: 1.37 | P2: 1.73 | R2: STRIPE | S2: 46125 | T2: 46128 | U2: Bottoms | V2: Cheryl Ortega | W2: 463 Valencia Key | Y2: Smithhaven | Z2: FL | AA2: 70198 | AB2: US | AC2: 0.97
A3: 46125 | B3: 12:30 PM | C3: 46100 | D3: No | F3: nthomas | G3: LOFT | H3: LOFT navy athletic accessorie in size l #athletic #navy #thrift #depop | I3: L | J3: 24.81 | K3: 3.99 | L3: 31.28 | M3: 0 | N3: 0 | O3: 1.96 | P3: 2.48 | R3: STRIPE | S3: 46127 | T3: 46130 | U3: Accessories | V3: Emma Porter | W3: 1521 Smith Village | Y3: West Javierfurt | Z3: OR | AA3: 44640 | AB3: US
A4: 46125 | B4: 2:24 PM | C4: 46113 | D4: No | F4: oarmstrong | G4: Other | H4: Other white lace bottom in size m #lace #white #thrift #depop | I4: M | J4: 26.62 | K4: 4.99 | L4: 34.27 | M4: 0 | N4: 0 | O4: 2.1 | P4: 2.66 | R4: STRIPE | S4: 46127 | T4: 46130 | U4: Bottoms | V4: Karen Jackson | W4: 378 Danny Underpass | Y4: Jonestown | Z4: IL | AA4: 75161 | AB4: US | AC4: 2.01
A5: 46126 | B5: 8:22 AM | C5: 46106 | D5: No | F5: derek63 | G5: Free People | H5: Free People green athletic coats/jacket in size s #athletic #green #thrift #depop | I5: S | J5: 7.42 | K5: 7.99 | L5: 16.15 | M5: 0 | N5: 0 | O5: 0.59 | P5: 0.74 | R5: STRIPE | S5: 46128 | T5: 46131 | U5: Coats/Jackets | V5: Valerie Bowman | W5: 8625 Nielsen Curve Apt. 961 | Y5: North Douglasburgh | Z5: NY | AA5: 23785 | AB5: US | AC5: 0.52
A6: 46128 | B6: 7:33 PM | C6: 46113 | D6: No | F6: mjames | G6: Old Navy | H6: Old Navy pink y2k swimwear in size s #y2k #pink #thrift #depop | I6: S | J6: 9 | K6: 3.99 | L6: 13.89 | M6: 0 | N6: 0 | O6: 0.71 | P6: 0.9 | R6: STRIPE | S6: 46130 | T6: 46133 | U6: Swimwear | V6: David Wolf | W6: 688 Shawna Overpass Apt. 699 | Y6: Port Rachel | Z6: OR | AA6: 49519 | AB6: US
A7: 46129 | B7: 3:27 PM | C7: 46102 | D7: No | F7: cynthia95 | G7: Express | H7: Express blue vintage coats/jacket in size l #vintage #blue #thrift #depop | I7: L | J7: 20.09 | K7: 5.99 | L7: 28.09 | M7: 0 | N7: 0 | O7: 1.59 | P7: 2.01 | R7: STRIPE | S7: 46131 | T7: 46134 | U7: Coats/Jackets | V7: Christopher Chapman | W7: 0058 Angela Highway | Y7: Port Scott | Z7: IL | AA7: 91666 | AB7: US | AC7: 1.34
A8: 46132 | B8: 11:38 AM | C8: 46123 | D8: No | F8: khanrobert | G8: Zara | H8: Zara gray y2k dresse in size xl #y2k #gray #thrift #depop | I8: XL | J8: 15.61 | K8: 6.49 | L8: 23.66 | M8: 0 | N8: 0 | O8: 1.23 | P8: 1.56 | R8: STRIPE | S8: 46134 | T8: 46137 | U8: Dresses | V8: Andrea Carter | W8: 8246 Ortiz Shoals Apt. 469 | Y8: Leemouth | Z8: OH | AA8: 26408 | AB8: US | AC8: 0.73
A9: 46133 | B9: 6:52 PM | C9: 46113 | D9: No | F9: nhensley | G9: Express | H9: Express pink casual swimwear in size l #casual #pink #thrift #depop | I9: L | J9: 26.67 | K9: 7.99 | L9: 37.33 | M9: 0 | N9: 0 | O9: 2.11 | P9: 2.67 | R9: STRIPE | S9: 46135 | T9: 46138 | U9: Swimwear | V9: Matthew Horn | W9: 81756 Joseph Avenue Suite 358 | Y9: South Aprilborough | Z9: OH | AA9: 79866 | AB9: US
A10: 46135 | B10: 5:25 PM | C10: 46111 | D10: No | F10: wdavila | G10: Old Navy | H10: Old Navy navy athletic bottom in size l #athletic #navy #thrift #depop | I10: L | J10: 15.16 | K10: 7.99 | L10: 24.67 | M10: 0 | N10: 0 | O10: 1.2 | P10: 1.52 | R10: STRIPE | S10: 46137 | T10: 46140 | U10: Bottoms | V10: Tristan Espinoza | W10: 282 Daniel Extension Suite 616 | Y10: East Kyletown | Z10: CA | AA10: 50447 | AB10: US | AC10: 0.67
A11: 46135 | B11: 1:57 PM | C11: 46119 | D11: No | F11: xcruz | G11: Express | H11: Express navy boho coats/jacket in size xs #boho #navy #thrift #depop | I11: XS | J11: 23.52 | K11: 6.49 | L11: 32.36 | M11: 0 | N11: 0 | O11: 1.86 | P11: 2.35 | R11: STRIPE | S11: 46137 | T11: 46140 | U11: Coats/Jackets | V11: Catherine Johnson | W11: 673 Nash Fork Suite 153 | Y11: South Kenneth | Z11: CA | AA11: 99002 | AB11: US | AC11: 1.56
A12: 46135 | B12: 7:25 PM | C12: 46124 | D12: No | F12: aaroncollins | G12: Express | H12: Express white athletic dresse in size s #athletic #white #thrift #depop | I12: S | J12: 13.63 | K12: 7.99 | L12: 22.98 | M12: 0 | N12: 0 | O12: 1.08 | P12: 1.36 | R12: STRIPE | S12: 46137 | T12: 46140 | U12: Dresses | V12: Nicole Jackson | W12: 46788 Gonzalez Brooks Apt. 419 | Y12: North Robertstad | Z12: PA | AA12: 73538 | AB12: US | AC12: 0.78
A13: 46135 | B13: 7:49 PM | C13: 46107 | D13: No | F13: james16 | G13: H&M | H13: H&M green athletic coats/jacket in size l #athletic #green #thrift #depop | I13: L | J13: 7.78 | K13: 3.99 | L13: 12.55 | M13: 0 | N13: 0 | O13: 0.61 | P13: 0.78 | R13: STRIPE | S13: 46137 | T13: 46140 | U13: Coats/Jackets | V13: Christopher Murray | W13: 76682 Wright Harbor | Y13: Armstrongfurt | Z13: GA | AA13: 24574 | AB13: US | AC13: 0.59
